[{"name": "This Is The Life", "popularity": 81, "explicit": false, "ranking": 1, "album_name": "This Is The Life (eDeluxe)", "album_release_date": "2007-01-01", "album_cover": "https://i.scdn.co/image/ab67616d0000b273aa2d1f1ecc9aa8f82fd56f7c", "album_url": "https://open.spotify.com/album/5DaToG3KvHnUgTPqY4cEbq", "danceability": 0.628, "energy": 0.882, "key": 1, "mode": 0, "speechiness": 0.0323, "acousticness": 0.259, "instrumentalness": 0, "liveness": 0.065, "valence": 0.853, "tempo": 95.083, "artist_name": "Amy Macdonald", "artist_url": "https://open.spotify.com/artist/1hJuGCUpefX24GFmss9bjH", "country": "Saudi Arabia"}, {"name": "Seven (feat. Latto) (Explicit Ver.)", "popularity": 96, "explicit": true, "ranking": 2, "album_name": "Seven (feat. Latto)", "album_release_date": "2023-07-14", "album_cover": "https://i.scdn.co/image/ab67616d0000b273bf5cce5a0e1ed03a626bdd74", "album_url": "https://open.spotify.com/album/53985D8g3JcGBoULSOYYKX", "danceability": 0.802, "energy": 0.832, "key": 11, "mode": 1, "speechiness": 0.0434, "acousticness": 0.311, "instrumentalness": 0, "liveness": 0.0815, "valence": 0.89, "tempo": 124.997, "artist_name": "Jung Kook", "artist_url": "https://open.spotify.com/artist/6HaGTQPmzraVmaVxvz6EUc", "country": "Saudi Arabia"}, {"name": "Bleeding", "popularity": 64, "explicit": false, "ranking": 3, "album_name": "Bleeding", "album_release_date": "2022-07-01", "album_cover": "https://i.scdn.co/image/ab67616d0000b273f3c34f462e19622aeeef2eac", "album_url": "https://open.spotify.com/album/1whfFAx345bRkQwi74NMlt", "danceability": 0.608, "energy": 0.443, "key": 9, "mode": 1, "speechiness": 0.0381, "acousticness": 0.771, "instrumentalness": 0.00127, "liveness": 0.112, "valence": 0.211, "tempo": 125.847, "artist_name": "TalkinToys", "artist_url": "https://open.spotify.com/artist/4HDTeSTvhHcxmdeKGKmCJy", "country": "Saudi Arabia"}, {"name": "3D (feat. Jack Harlow)", "popularity": 89, "explicit": true, "ranking": 4, "album_name": "3D : The Remixes", "album_release_date": "2023-10-02", "album_cover": "https://i.scdn.co/image/ab67616d0000b27399583bb32b47e87d55c6064b", "album_url": "https://open.spotify.com/album/0fJ0beklzFwoBv01U8792s", "danceability": 0.853, "energy": 0.824, "key": 1, "mode": 1, "speechiness": 0.103, "acousticness": 0.0322, "instrumentalness": 0, "liveness": 0.0859, "valence": 0.888, "tempo": 108.044, "artist_name": "Jung Kook", "artist_url": "https://open.spotify.com/artist/6HaGTQPmzraVmaVxvz6EUc", "country": "Saudi Arabia"}, {"name": "My Love Mine All Mine", "popularity": 97, "explicit": false, "ranking": 5, "album_name": "The Land Is Inhospitable and So Are We", "album_release_date": "2023-09-15", "album_cover": "https://i.scdn.co/image/ab67616d0000b27334f21d3047d85440dfa37f10", "album_url": "https://open.spotify.com/album/2Cn1d2KgbkAqbZCJ1RzdkA", "danceability": 0.504, "energy": 0.308, "key": 9, "mode": 1, "speechiness": 0.0321, "acousticness": 0.868, "instrumentalness": 0.135, "liveness": 0.158, "valence": 0.121, "tempo": 113.95, "artist_name": "Mitski", "artist_url": "https://open.spotify.com/artist/2uYWxilOVlUdk4oV9DvwqK", "country": "Saudi Arabia"}, {"name": "Set Fire to the Rain", "popularity": 83, "explicit": false, "ranking": 6, "album_name": "21", "album_release_date": "2011-01-24", "album_cover": "https://i.scdn.co/image/ab67616d0000b2732118bf9b198b05a95ded6300", "album_url": "https://open.spotify.com/album/0Lg1uZvI312TPqxNWShFXL", "danceability": 0.603, "energy": 0.67, "key": 2, "mode": 0, "speechiness": 0.0249, "acousticness": 0.00408, "instrumentalness": 1.68e-06, "liveness": 0.112, "valence": 0.446, "tempo": 107.993, "artist_name": "Adele", "artist_url": "https://open.spotify.com/artist/4dpARuHxo51G3z768sgnrY", "country": "Saudi Arabia"}, {"name": "This Is The Life - Sped Up Version", "popularity": 68, "explicit": false, "ranking": 7, "album_name": "This Is The Life (Sped Up Version)", "album_release_date": "2023-04-28", "album_cover": "https://i.scdn.co/image/ab67616d0000b273a4297c019d46a105ca6f99de", "album_url": "https://open.spotify.com/album/6jWUKD3FTfLXCzJ1bzuBIL", "danceability": 0.634, "energy": 0.955, "key": 10, "mode": 1, "speechiness": 0.0771, "acousticness": 0.22, "instrumentalness": 0, "liveness": 0.117, "valence": 0.716, "tempo": 103.613, "artist_name": "Amy Macdonald", "artist_url": "https://open.spotify.com/artist/1hJuGCUpefX24GFmss9bjH", "country": "Saudi Arabia"}, {"name": "greedy", "popularity": 100, "explicit": true, "ranking": 8, "album_name": "greedy", "album_release_date": "2023-09-15", "album_cover": "https://i.scdn.co/image/ab67616d0000b27322fd802bc61db666c7c81aa8", "album_url": "https://open.spotify.com/album/3UOV8XvCwMKaATRNXrYCjN", "danceability": 0.75, "energy": 0.733, "key": 6, "mode": 0, "speechiness": 0.0319, "acousticness": 0.256, "instrumentalness": 0, "liveness": 0.114, "valence": 0.844, "tempo": 111.018, "artist_name": "Tate McRae", "artist_url": "https://open.spotify.com/artist/45dkTj5sMRSjrmBSBeiHym", "country": "Saudi Arabia"}, {"name": "Love Me Again", "popularity": 90, "explicit": false, "ranking": 9, "album_name": "Layover", "album_release_date": "2023-08-11", "album_cover": "https://i.scdn.co/image/ab67616d0000b2732f1a5b69c2bd76474bca8035", "album_url": "https://open.spotify.com/album/1ZBDI1LqnuAKdrePUF2D5m", "danceability": 0.633, "energy": 0.607, "key": 0, "mode": 0, "speechiness": 0.0532, "acousticness": 0.183, "instrumentalness": 1.38e-06, "liveness": 0.167, "valence": 0.363, "tempo": 74.029, "artist_name": "V", "artist_url": "https://open.spotify.com/artist/3JsHnjpbhX4SnySpvpa9DK", "country": "Saudi Arabia"}, {"name": "Paint The Town Red", "popularity": 89, "explicit": true, "ranking": 10, "album_name": "Scarlet", "album_release_date": "2023-09-20", "album_cover": "https://i.scdn.co/image/ab67616d0000b273a840032f14ab22da396e43cb", "album_url": "https://open.spotify.com/album/1bBez9PNvkJPW08bU7NYta", "danceability": 0.864, "energy": 0.556, "key": 2, "mode": 0, "speechiness": 0.194, "acousticness": 0.255, "instrumentalness": 3.85e-06, "liveness": 0.112, "valence": 0.726, "tempo": 99.974, "artist_name": "Doja Cat", "artist_url": "https://open.spotify.com/artist/5cj0lLjcoR7YOSnhnX0Po5", "country": "Saudi Arabia"}, {"name": "Strangers", "popularity": 98, "explicit": false, "ranking": 11, "album_name": "Strangers", "album_release_date": "2023-09-01", "album_cover": "https://i.scdn.co/image/ab67616d0000b2734756c2e9ae436437cd75e9f3", "album_url": "https://open.spotify.com/album/18ogtNq9F7DmMkNYO6Xb4k", "danceability": 0.628, "energy": 0.523, "key": 11, "mode": 0, "speechiness": 0.0946, "acousticness": 0.701, "instrumentalness": 0.00274, "liveness": 0.219, "valence": 0.416, "tempo": 169.982, "artist_name": "Kenya Grace", "artist_url": "https://open.spotify.com/artist/7uMDnSZyUYNBPLhPMNuaM2", "country": "Saudi Arabia"}, {"name": "TOO MUCH", "popularity": 92, "explicit": true, "ranking": 12, "album_name": "TOO MUCH", "album_release_date": "2023-10-19", "album_cover": "https://i.scdn.co/image/ab67616d0000b273389e41e5096b6112ce0e1008", "album_url": "https://open.spotify.com/album/7gCggwpSuqUmVzWniLdpKR", "danceability": 0.758, "energy": 0.703, "key": 10, "mode": 0, "speechiness": 0.172, "acousticness": 0.252, "instrumentalness": 0, "liveness": 0.146, "valence": 0.465, "tempo": 94.985, "artist_name": "The Kid LAROI", "artist_url": "https://open.spotify.com/artist/2tIP7SsRs7vjIcLrU85W8J", "country": "Saudi Arabia"}, {"name": "Daylight", "popularity": 95, "explicit": false, "ranking": 13, "album_name": "Daylight", "album_release_date": "2023-04-14", "album_cover": "https://i.scdn.co/image/ab67616d0000b27395ca6a9b4083a86c149934ae", "album_url": "https://open.spotify.com/album/6NcI39WPu4kY6Tul11nhSv", "danceability": 0.508, "energy": 0.43, "key": 2, "mode": 0, "speechiness": 0.0335, "acousticness": 0.83, "instrumentalness": 0.000441, "liveness": 0.093, "valence": 0.324, "tempo": 130.09, "artist_name": "David Kushner", "artist_url": "https://open.spotify.com/artist/33NVpKoXjItPwUJTMZIOiY", "country": "Saudi Arabia"}, {"name": "Is It Over Now? (Taylor's Version) (From The Vault)", "popularity": 93, "explicit": false, "ranking": 14, "album_name": "1989 (Taylor's Version)", "album_release_date": "2023-10-26", "album_cover": "https://i.scdn.co/image/ab67616d0000b273904445d70d04eb24d6bb79ac", "album_url": "https://open.spotify.com/album/64LU4c1nfjz1t4VnGhagcg", "danceability": 0.596, "energy": 0.658, "key": 0, "mode": 1, "speechiness": 0.036, "acousticness": 0.0504, "instrumentalness": 0, "liveness": 0.127, "valence": 0.176, "tempo": 100.012, "artist_name": "Taylor Swift", "artist_url": "https://open.spotify.com/artist/06HL4z0CvFAxyc27GXpf02", "country": "Saudi Arabia"}, {"name": "Slow Dancing", "popularity": 96, "explicit": false, "ranking": 15, "album_name": "Layover", "album_release_date": "2023-09-08", "album_cover": "https://i.scdn.co/image/ab67616d0000b2738e504c5aedaae49a73ed4963", "album_url": "https://open.spotify.com/album/7ixOAT89NSsgUITYc5ByB5", "danceability": 0.579, "energy": 0.63, "key": 8, "mode": 1, "speechiness": 0.058, "acousticness": 0.257, "instrumentalness": 0.00462, "liveness": 0.0986, "valence": 0.552, "tempo": 155.96, "artist_name": "V", "artist_url": "https://open.spotify.com/artist/3JsHnjpbhX4SnySpvpa9DK", "country": "Saudi Arabia"}, {"name": "\u064a\u0627\u062d\u0644\u0648\u0647 \u064a\u0627 \u0645\u0638\u0644\u0648\u0645\u0647", "popularity": 50, "explicit": false, "ranking": 16, "album_name": "\u064a\u0627\u062d\u0644\u0648\u0647 \u064a\u0627 \u0645\u0638\u0644\u0648\u0645\u0647", "album_release_date": "2010-05-17", "album_cover": "https://i.scdn.co/image/ab67616d0000b273a7b85d126411cc165768a0a3", "album_url": "https://open.spotify.com/album/0IDO9jvpOUsUudouAEDp1G", "danceability": 0.544, "energy": 0.992, "key": 9, "mode": 0, "speechiness": 0.0424, "acousticness": 0.196, "instrumentalness": 0, "liveness": 0.27, "valence": 0.968, "tempo": 149.957, "artist_name": "\u0627\u0628\u0648 \u0633\u0631\u0627\u062c", "artist_url": "https://open.spotify.com/artist/0vpmKeQKsemdWl7keerMxD", "country": "Saudi Arabia"}, {"name": "I Wanna Be Yours", "popularity": 95, "explicit": false, "ranking": 17, "album_name": "AM", "album_release_date": "2013-09-09", "album_cover": "https://i.scdn.co/image/ab67616d0000b2734ae1c4c5c45aabe565499163", "album_url": "https://open.spotify.com/album/78bpIziExqiI9qztvNFlQu", "danceability": 0.464, "energy": 0.417, "key": 0, "mode": 0, "speechiness": 0.0256, "acousticness": 0.136, "instrumentalness": 0.022, "liveness": 0.0974, "valence": 0.479, "tempo": 67.528, "artist_name": "Arctic Monkeys", "artist_url": "https://open.spotify.com/artist/7Ln80lUS6He07XvHI8qqHH", "country": "Saudi Arabia"}, {"name": "\"Slut!\" (Taylor's Version) (From The Vault)", "popularity": 91, "explicit": false, "ranking": 18, "album_name": "1989 (Taylor's Version)", "album_release_date": "2023-10-26", "album_cover": "https://i.scdn.co/image/ab67616d0000b273904445d70d04eb24d6bb79ac", "album_url": "https://open.spotify.com/album/64LU4c1nfjz1t4VnGhagcg", "danceability": 0.629, "energy": 0.413, "key": 7, "mode": 1, "speechiness": 0.055, "acousticness": 0.345, "instrumentalness": 7.62e-05, "liveness": 0.0603, "valence": 0.306, "tempo": 77.983, "artist_name": "Taylor Swift", "artist_url": "https://open.spotify.com/artist/06HL4z0CvFAxyc27GXpf02", "country": "Saudi Arabia"}, {"name": "ecstacy (slowed)", "popularity": 90, "explicit": true, "ranking": 19, "album_name": "ecstacy (slowed)", "album_release_date": "2023-06-06", "album_cover": "https://i.scdn.co/image/ab67616d0000b273cddfe70492c57a78e4d86b1c", "album_url": "https://open.spotify.com/album/6KLSjdqyjISLUhW8bx0Bqi", "danceability": 0.551, "energy": 0.677, "key": 2, "mode": 1, "speechiness": 0.0665, "acousticness": 0.0173, "instrumentalness": 0, "liveness": 0.381, "valence": 0.195, "tempo": 106.414, "artist_name": "SUICIDAL-IDOL", "artist_url": "https://open.spotify.com/artist/6KOszWgIriJLaPOySuBOTI", "country": "Saudi Arabia"}, {"name": "Agora Hills", "popularity": 82, "explicit": true, "ranking": 20, "album_name": "Scarlet", "album_release_date": "2023-09-20", "album_cover": "https://i.scdn.co/image/ab67616d0000b273a840032f14ab22da396e43cb", "album_url": "https://open.spotify.com/album/1bBez9PNvkJPW08bU7NYta", "danceability": 0.755, "energy": 0.687, "key": 8, "mode": 0, "speechiness": 0.101, "acousticness": 0.183, "instrumentalness": 0.000177, "liveness": 0.125, "valence": 0.381, "tempo": 123.01, "artist_name": "Doja Cat", "artist_url": "https://open.spotify.com/artist/5cj0lLjcoR7YOSnhnX0Po5", "country": "Saudi Arabia"}, {"name": "Diamonds", "popularity": 78, "explicit": false, "ranking": 21, "album_name": "Unapologetic (Edited Version)", "album_release_date": "2012-01-01", "album_cover": "https://i.scdn.co/image/ab67616d0000b273e24cbbd5cef05ca77ec67df6", "album_url": "https://open.spotify.com/album/0T23GvNaBUGtMKxZko8LQG", "danceability": 0.564, "energy": 0.71, "key": 11, "mode": 0, "speechiness": 0.0461, "acousticness": 0.00125, "instrumentalness": 0, "liveness": 0.109, "valence": 0.393, "tempo": 91.972, "artist_name": "Rihanna", "artist_url": "https://open.spotify.com/artist/5pKCCKE2ajJHZ9KAiaK11H", "country": "Saudi Arabia"}, {"name": "\u0643\u0644\u0627\u0645 \u0639\u064a\u0646\u064a\u0647", "popularity": 77, "explicit": false, "ranking": 22, "album_name": "\u0646\u0633\u0627\u0649", "album_release_date": "2018-10-24", "album_cover": "https://i.scdn.co/image/ab67616d0000b273cfa4e906cda39d8f62fe81e3", "album_url": "https://open.spotify.com/album/1aCq7XjXXVc3WxPYYUrbeP", "danceability": 0.573, "energy": 0.759, "key": 1, "mode": 0, "speechiness": 0.0428, "acousticness": 0.0477, "instrumentalness": 1.37e-06, "liveness": 0.193, "valence": 0.745, "tempo": 131.931, "artist_name": "Sherine", "artist_url": "https://open.spotify.com/artist/2Wk167T0fY1fABsHM5qFcI", "country": "Saudi Arabia"}, {"name": "Freed From Desire - prod. Molella, Phil Jay", "popularity": 81, "explicit": false, "ranking": 23, "album_name": "Come Into My Life (The Album)", "album_release_date": "1997-11-17", "album_cover": "https://i.scdn.co/image/ab67616d0000b273e3a26492e5b3a5f37021bd2d", "album_url": "https://open.spotify.com/album/3vcwGUl0WiJVssOR1dXEbe", "danceability": 0.704, "energy": 0.861, "key": 2, "mode": 0, "speechiness": 0.0493, "acousticness": 0.587, "instrumentalness": 0.0615, "liveness": 0.0992, "valence": 0.636, "tempo": 128.99, "artist_name": "Gala", "artist_url": "https://open.spotify.com/artist/3OqTvcWgb0xaainosGVvuZ", "country": "Saudi Arabia"}, {"name": "Say Don't Go (Taylor's Version) (From The Vault)", "popularity": 90, "explicit": false, "ranking": 24, "album_name": "1989 (Taylor's Version)", "album_release_date": "2023-10-26", "album_cover": "https://i.scdn.co/image/ab67616d0000b273904445d70d04eb24d6bb79ac", "album_url": "https://open.spotify.com/album/64LU4c1nfjz1t4VnGhagcg", "danceability": 0.626, "energy": 0.547, "key": 4, "mode": 1, "speechiness": 0.0342, "acousticness": 0.0656, "instrumentalness": 1.67e-05, "liveness": 0.149, "valence": 0.192, "tempo": 109.946, "artist_name": "Taylor Swift", "artist_url": "https://open.spotify.com/artist/06HL4z0CvFAxyc27GXpf02", "country": "Saudi Arabia"}, {"name": "Cruel Summer", "popularity": 99, "explicit": false, "ranking": 25, "album_name": "Lover", "album_release_date": "2019-08-23", "album_cover": "https://i.scdn.co/image/ab67616d0000b273e787cffec20aa2a396a61647", "album_url": "https://open.spotify.com/album/1NAmidJlEaVgA3MpcPFYGq", "danceability": 0.552, "energy": 0.702, "key": 9, "mode": 1, "speechiness": 0.157, "acousticness": 0.117, "instrumentalness": 2.06e-05, "liveness": 0.105, "valence": 0.564, "tempo": 169.994, "artist_name": "Taylor Swift", "artist_url": "https://open.spotify.com/artist/06HL4z0CvFAxyc27GXpf02", "country": "Saudi Arabia"}, {"name": "Style (Taylor's Version)", "popularity": 90, "explicit": false, "ranking": 26, "album_name": "1989 (Taylor's Version)", "album_release_date": "2023-10-26", "album_cover": "https://i.scdn.co/image/ab67616d0000b273904445d70d04eb24d6bb79ac", "album_url": "https://open.spotify.com/album/64LU4c1nfjz1t4VnGhagcg", "danceability": 0.575, "energy": 0.824, "key": 2, "mode": 1, "speechiness": 0.038, "acousticness": 0.000418, "instrumentalness": 0.0214, "liveness": 0.0901, "valence": 0.292, "tempo": 94.971, "artist_name": "Taylor Swift", "artist_url": "https://open.spotify.com/artist/06HL4z0CvFAxyc27GXpf02", "country": "Saudi Arabia"}, {"name": "Summertime Sadness", "popularity": 78, "explicit": false, "ranking": 27, "album_name": "Born To Die \u2013 Paradise Edition (Special Version)", "album_release_date": "2012-01-01", "album_cover": "https://i.scdn.co/image/ab67616d0000b273f894be72a77b1488292672c7", "album_url": "https://open.spotify.com/album/0Dt3FbpMQwjoT5KNAw0IXR", "danceability": 0.566, "energy": 0.647, "key": 1, "mode": 0, "speechiness": 0.0335, "acousticness": 0.0477, "instrumentalness": 0, "liveness": 0.121, "valence": 0.22, "tempo": 111.96, "artist_name": "Lana Del Rey", "artist_url": "https://open.spotify.com/artist/00FQb4jTyendYWaN8pK0wa", "country": "Saudi Arabia"}, {"name": "Apocalypse", "popularity": 90, "explicit": false, "ranking": 28, "album_name": "Cigarettes After Sex", "album_release_date": "2017-06-09", "album_cover": "https://i.scdn.co/image/ab67616d0000b27312b69bf576f5e80291f75161", "album_url": "https://open.spotify.com/album/2mxFsS5yylSTHNivV53HoA", "danceability": 0.37, "energy": 0.467, "key": 5, "mode": 1, "speechiness": 0.0273, "acousticness": 0.0205, "instrumentalness": 0.572, "liveness": 0.109, "valence": 0.182, "tempo": 94.485, "artist_name": "Cigarettes After Sex", "artist_url": "https://open.spotify.com/artist/1QAJqy2dA3ihHBFIHRphZj", "country": "Saudi Arabia"}, {"name": "Automotivo Bibi Fogosa", "popularity": 89, "explicit": true, "ranking": 29, "album_name": "Automotivo Bibi Fogosa", "album_release_date": "2023-05-19", "album_cover": "https://i.scdn.co/image/ab67616d0000b273530b46efc7157d71389648f2", "album_url": "https://open.spotify.com/album/0Hj2X0CQBjpWapFzNQGbk2", "danceability": 0.726, "energy": 0.873, "key": 9, "mode": 1, "speechiness": 0.0266, "acousticness": 0.2, "instrumentalness": 1.71e-06, "liveness": 0.0953, "valence": 0.725, "tempo": 135.052, "artist_name": "Bibi Babydoll", "artist_url": "https://open.spotify.com/artist/6R26kGib2ubbZJMh7kKVGV", "country": "Saudi Arabia"}, {"name": "MONTAGEM - PR FUNK", "popularity": 88, "explicit": false, "ranking": 30, "album_name": "MONTAGEM - PR FUNK", "album_release_date": "2023-05-01", "album_cover": "https://i.scdn.co/image/ab67616d0000b2736a922a01d3fb1c53873b1f9d", "album_url": "https://open.spotify.com/album/2HuMAoXpr6HDryNHipbCpB", "danceability": 0.877, "energy": 0.803, "key": 9, "mode": 1, "speechiness": 0.0507, "acousticness": 0.734, "instrumentalness": 0.056, "liveness": 0.087, "valence": 0.795, "tempo": 130.028, "artist_name": "S3BZS", "artist_url": "https://open.spotify.com/artist/6zFMFB1JvNHkHvCSudF4id", "country": "Saudi Arabia"}, {"name": "Now That We Don't Talk (Taylor's Version) (From The Vault)", "popularity": 91, "explicit": false, "ranking": 31, "album_name": "1989 (Taylor's Version)", "album_release_date": "2023-10-26", "album_cover": "https://i.scdn.co/image/ab67616d0000b273904445d70d04eb24d6bb79ac", "album_url": "https://open.spotify.com/album/64LU4c1nfjz1t4VnGhagcg", "danceability": 0.793, "energy": 0.512, "key": 0, "mode": 1, "speechiness": 0.0338, "acousticness": 0.186, "instrumentalness": 3.81e-05, "liveness": 0.0889, "valence": 0.0662, "tempo": 109.994, "artist_name": "Taylor Swift", "artist_url": "https://open.spotify.com/artist/06HL4z0CvFAxyc27GXpf02", "country": "Saudi Arabia"}, {"name": "METAMORPHOSIS", "popularity": 88, "explicit": true, "ranking": 32, "album_name": "METAMORPHOSIS", "album_release_date": "2021-11-25", "album_cover": "https://i.scdn.co/image/ab67616d0000b273b852a616ae3a49a1f6b0f16e", "album_url": "https://open.spotify.com/album/3apQZbgVql9mHJlp43jk5D", "danceability": 0.593, "energy": 0.641, "key": 7, "mode": 0, "speechiness": 0.0992, "acousticness": 0.426, "instrumentalness": 0.901, "liveness": 0.122, "valence": 0.147, "tempo": 175.014, "artist_name": "INTERWORLD", "artist_url": "https://open.spotify.com/artist/5hKGLu4Ik88FzWcTPhWNTN", "country": "Saudi Arabia"}, {"name": "Another Love", "popularity": 92, "explicit": true, "ranking": 33, "album_name": "Long Way Down (Deluxe)", "album_release_date": "2013-06-24", "album_cover": "https://i.scdn.co/image/ab67616d0000b2731917a0f3f4152622a040913f", "album_url": "https://open.spotify.com/album/0Gf1yE895FKK4YWVRuAeg8", "danceability": 0.445, "energy": 0.537, "key": 4, "mode": 0, "speechiness": 0.04, "acousticness": 0.695, "instrumentalness": 1.65e-05, "liveness": 0.0944, "valence": 0.131, "tempo": 122.769, "artist_name": "Tom Odell", "artist_url": "https://open.spotify.com/artist/2txHhyCwHjUEpJjWrEyqyX", "country": "Saudi Arabia"}, {"name": "LOVELY BASTARDS", "popularity": 88, "explicit": true, "ranking": 34, "album_name": "LOVELY BASTARDS", "album_release_date": "2023-08-25", "album_cover": "https://i.scdn.co/image/ab67616d0000b273226383907a53ab4c13cca8e2", "album_url": "https://open.spotify.com/album/2b3Kiolsu42XiVvhRmTEsM", "danceability": 0.613, "energy": 0.81, "key": 1, "mode": 1, "speechiness": 0.488, "acousticness": 0.832, "instrumentalness": 0.899, "liveness": 0.137, "valence": 0.686, "tempo": 150.251, "artist_name": "ZWE1HVNDXR", "artist_url": "https://open.spotify.com/artist/33rnQWadiG2aauIwIxPxfB", "country": "Saudi Arabia"}, {"name": "\u0627\u0633\u0623\u0644 \u0639\u0646\u064a \u0645\u064a\u062a \u0639\u0627\u064a\u0634 - \u0645\u0633\u0631\u0639", "popularity": 50, "explicit": false, "ranking": 35, "album_name": "\u0627\u0633\u0623\u0644 \u0639\u0646\u064a \u0645\u064a\u062a \u0639\u0627\u064a\u0634 - \u0645\u0633\u0631\u0639", "album_release_date": "2023-10-14", "album_cover": "https://i.scdn.co/image/ab67616d0000b2732a188a8d33fa9bb998028b74", "album_url": "https://open.spotify.com/album/4LV8mO2MMI6zuThoozHB60", "danceability": 0.587, "energy": 0.839, "key": 8, "mode": 1, "speechiness": 0.252, "acousticness": 0.0543, "instrumentalness": 5.77e-06, "liveness": 0.269, "valence": 0.739, "tempo": 104.447, "artist_name": "MaqamMusic", "artist_url": "https://open.spotify.com/artist/7BEbEqXU1xU7Uw0lO7jfme", "country": "Saudi Arabia"}, {"name": "fukumean", "popularity": 95, "explicit": true, "ranking": 36, "album_name": "a Gift & a Curse", "album_release_date": "2023-06-16", "album_cover": "https://i.scdn.co/image/ab67616d0000b273017d5e26552345c4b1575b6c", "album_url": "https://open.spotify.com/album/5qmZefgh78fN3jsyPPlvuw", "danceability": 0.847, "energy": 0.622, "key": 1, "mode": 0, "speechiness": 0.0903, "acousticness": 0.119, "instrumentalness": 0, "liveness": 0.285, "valence": 0.22, "tempo": 130.001, "artist_name": "Gunna", "artist_url": "https://open.spotify.com/artist/2hlmm7s2ICUX0LVIhVFlZQ", "country": "Saudi Arabia"}, {"name": "One Of The Girls (with JENNIE, Lily Rose Depp)", "popularity": 90, "explicit": false, "ranking": 37, "album_name": "The Idol Episode 4 (Music from the HBO Original Series)", "album_release_date": "2023-06-23", "album_cover": "https://i.scdn.co/image/ab67616d0000b273b0dd6a5cd1dec96c4119c262", "album_url": "https://open.spotify.com/album/7tzVd1fwkxsorytCBjEJkU", "danceability": 0.522, "energy": 0.641, "key": 8, "mode": 1, "speechiness": 0.0318, "acousticness": 0.0545, "instrumentalness": 0, "liveness": 0.162, "valence": 0.202, "tempo": 87.51, "artist_name": "The Weeknd", "artist_url": "https://open.spotify.com/artist/1Xyo4u8uXC1ZmMpatF05PJ", "country": "Saudi Arabia"}, {"name": "we fell in love in october", "popularity": 91, "explicit": false, "ranking": 38, "album_name": "we fell in love in october / October Passed Me By", "album_release_date": "2018-11-21", "album_cover": "https://i.scdn.co/image/ab67616d0000b273d6839051c4760457e1a60b2a", "album_url": "https://open.spotify.com/album/7vud0sY43VTv28MbWiglDa", "danceability": 0.566, "energy": 0.366, "key": 7, "mode": 1, "speechiness": 0.028, "acousticness": 0.113, "instrumentalness": 0.181, "liveness": 0.155, "valence": 0.237, "tempo": 129.96, "artist_name": "girl in red", "artist_url": "https://open.spotify.com/artist/3uwAm6vQy7kWPS2bciKWx9", "country": "Saudi Arabia"}, {"name": "Rainy Days", "popularity": 86, "explicit": false, "ranking": 39, "album_name": "Layover", "album_release_date": "2023-08-11", "album_cover": "https://i.scdn.co/image/ab67616d0000b2732f1a5b69c2bd76474bca8035", "album_url": "https://open.spotify.com/album/1ZBDI1LqnuAKdrePUF2D5m", "danceability": 0.633, "energy": 0.454, "key": 9, "mode": 0, "speechiness": 0.0875, "acousticness": 0.739, "instrumentalness": 0, "liveness": 0.148, "valence": 0.282, "tempo": 74.828, "artist_name": "V", "artist_url": "https://open.spotify.com/artist/3JsHnjpbhX4SnySpvpa9DK", "country": "Saudi Arabia"}, {"name": "Starboy", "popularity": 94, "explicit": true, "ranking": 40, "album_name": "Starboy", "album_release_date": "2016-11-25", "album_cover": "https://i.scdn.co/image/ab67616d0000b2734718e2b124f79258be7bc452", "album_url": "https://open.spotify.com/album/2ODvWsOgouMbaA5xf0RkJe", "danceability": 0.679, "energy": 0.587, "key": 7, "mode": 1, "speechiness": 0.276, "acousticness": 0.141, "instrumentalness": 6.35e-06, "liveness": 0.137, "valence": 0.486, "tempo": 186.003, "artist_name": "The Weeknd", "artist_url": "https://open.spotify.com/artist/1Xyo4u8uXC1ZmMpatF05PJ", "country": "Saudi Arabia"}, {"name": "Like Crazy", "popularity": 94, "explicit": false, "ranking": 41, "album_name": "FACE", "album_release_date": "2023-03-24", "album_cover": "https://i.scdn.co/image/ab67616d0000b2732b46078245d0120690eb560d", "album_url": "https://open.spotify.com/album/4xc3Lc9yASZgEJGH7acWMB", "danceability": 0.629, "energy": 0.733, "key": 7, "mode": 1, "speechiness": 0.0419, "acousticness": 0.0025, "instrumentalness": 0, "liveness": 0.357, "valence": 0.362, "tempo": 120.001, "artist_name": "Jimin", "artist_url": "https://open.spotify.com/artist/1oSPZhvZMIrWW5I41kPkkY", "country": "Saudi Arabia"}, {"name": "Kill Bill", "popularity": 92, "explicit": false, "ranking": 42, "album_name": "SOS", "album_release_date": "2022-12-08", "album_cover": "https://i.scdn.co/image/ab67616d0000b2730c471c36970b9406233842a5", "album_url": "https://open.spotify.com/album/1nrVofqDRs7cpWXJ49qTnP", "danceability": 0.644, "energy": 0.735, "key": 8, "mode": 1, "speechiness": 0.0391, "acousticness": 0.0521, "instrumentalness": 0.144, "liveness": 0.161, "valence": 0.418, "tempo": 88.98, "artist_name": "SZA", "artist_url": "https://open.spotify.com/artist/7tYKF4w9nC0nq9CsPZTHyP", "country": "Saudi Arabia"}, {"name": "Sweater Weather", "popularity": 93, "explicit": false, "ranking": 43, "album_name": "I Love You.", "album_release_date": "2013-04-19", "album_cover": "https://i.scdn.co/image/ab67616d0000b2738265a736a1eb838ad5a0b921", "album_url": "https://open.spotify.com/album/4xkM0BwLM9H2IUcbYzpcBI", "danceability": 0.612, "energy": 0.807, "key": 10, "mode": 1, "speechiness": 0.0336, "acousticness": 0.0495, "instrumentalness": 0.0177, "liveness": 0.101, "valence": 0.398, "tempo": 124.053, "artist_name": "The Neighbourhood", "artist_url": "https://open.spotify.com/artist/77SW9BnxLY8rJ0RciFqkHh", "country": "Saudi Arabia"}, {"name": "Blank Space (Taylor's Version)", "popularity": 89, "explicit": false, "ranking": 44, "album_name": "1989 (Taylor's Version)", "album_release_date": "2023-10-26", "album_cover": "https://i.scdn.co/image/ab67616d0000b273904445d70d04eb24d6bb79ac", "album_url": "https://open.spotify.com/album/64LU4c1nfjz1t4VnGhagcg", "danceability": 0.737, "energy": 0.725, "key": 0, "mode": 1, "speechiness": 0.0641, "acousticness": 0.0976, "instrumentalness": 0, "liveness": 0.174, "valence": 0.755, "tempo": 96.012, "artist_name": "Taylor Swift", "artist_url": "https://open.spotify.com/artist/06HL4z0CvFAxyc27GXpf02", "country": "Saudi Arabia"}, {"name": "Cry", "popularity": 85, "explicit": false, "ranking": 45, "album_name": "Cry", "album_release_date": "2019-10-25", "album_cover": "https://i.scdn.co/image/ab67616d0000b273fd275af89cec73d6287f9cbf", "album_url": "https://open.spotify.com/album/4uQ5kFmXQdCxz3WvM4UUzy", "danceability": 0.406, "energy": 0.399, "key": 7, "mode": 1, "speechiness": 0.0278, "acousticness": 0.756, "instrumentalness": 0.678, "liveness": 0.112, "valence": 0.163, "tempo": 142.83, "artist_name": "Cigarettes After Sex", "artist_url": "https://open.spotify.com/artist/1QAJqy2dA3ihHBFIHRphZj", "country": "Saudi Arabia"}, {"name": "The Color Violet", "popularity": 89, "explicit": false, "ranking": 46, "album_name": "Alone At Prom", "album_release_date": "2021-12-10", "album_cover": "https://i.scdn.co/image/ab67616d0000b2730c5f23cbf0b1ab7e37d0dc67", "album_url": "https://open.spotify.com/album/5Gm2XKBgnlzd6qTi7LE1z2", "danceability": 0.645, "energy": 0.534, "key": 6, "mode": 0, "speechiness": 0.0479, "acousticness": 0.157, "instrumentalness": 0, "liveness": 0.0863, "valence": 0.463, "tempo": 105.02, "artist_name": "Tory Lanez", "artist_url": "https://open.spotify.com/artist/2jku7tDXc6XoB6MO2hFuqg", "country": "Saudi Arabia"}, {"name": "\u0648\u064a\u0646 \u0635\u0631\u062a\u064a", "popularity": 53, "explicit": false, "ranking": 47, "album_name": "\u0648\u064a\u0646 \u0635\u0631\u062a\u064a", "album_release_date": "2016-06-23", "album_cover": "https://i.scdn.co/image/ab67616d0000b273ac868317ebe8b5258a6fc1d6", "album_url": "https://open.spotify.com/album/0aHapfQB1j8j0NefL50PDo", "danceability": 0.583, "energy": 0.879, "key": 1, "mode": 1, "speechiness": 0.0829, "acousticness": 0.0927, "instrumentalness": 2.5e-06, "liveness": 0.566, "valence": 0.507, "tempo": 103.929, "artist_name": "Raad And Methaq", "artist_url": "https://open.spotify.com/artist/2TS6Y2HXkANqlIC7ZNi5zq", "country": "Saudi Arabia"}, {"name": "Style", "popularity": 82, "explicit": false, "ranking": 48, "album_name": "1989", "album_release_date": "2014-10-27", "album_cover": "https://i.scdn.co/image/ab67616d0000b2739abdf14e6058bd3903686148", "album_url": "https://open.spotify.com/album/2QJmrSgbdM35R67eoGQo4j", "danceability": 0.598, "energy": 0.786, "key": 2, "mode": 1, "speechiness": 0.0383, "acousticness": 0.00253, "instrumentalness": 0.0016, "liveness": 0.117, "valence": 0.456, "tempo": 95.019, "artist_name": "Taylor Swift", "artist_url": "https://open.spotify.com/artist/06HL4z0CvFAxyc27GXpf02", "country": "Saudi Arabia"}, {"name": "\u064a\u0627 \u0627\u0628\u0646 \u0627\u0644\u0623\u0648\u0627\u062f\u0645", "popularity": 42, "explicit": false, "ranking": 49, "album_name": "\u0639\u0627\u0644\u0645 \u0645\u0648\u0627\u0632\u064a", "album_release_date": "2021-09-02", "album_cover": "https://i.scdn.co/image/ab67616d0000b273f5b0f2d811a3827de9db203b", "album_url": "https://open.spotify.com/album/3wewNeaWmRu0BLcxGdBinQ", "danceability": 0.679, "energy": 0.792, "key": 4, "mode": 0, "speechiness": 0.0594, "acousticness": 0.228, "instrumentalness": 0, "liveness": 0.267, "valence": 0.681, "tempo": 114.26, "artist_name": "Abdul Majeed Abdullah", "artist_url": "https://open.spotify.com/artist/2RxCv6j8Wu2rYbmtOBvg6F", "country": "Saudi Arabia"}, {"name": "Perfect Night", "popularity": 87, "explicit": false, "ranking": 50, "album_name": "Perfect Night", "album_release_date": "2023-10-27", "album_cover": "https://i.scdn.co/image/ab67616d0000b2735e352f6eccf8cb96d0b247cc", "album_url": "https://open.spotify.com/album/6Msc3BwzKZ5f5FXmKuUSu6", "danceability": 0.697, "energy": 0.82, "key": 5, "mode": 1, "speechiness": 0.0308, "acousticness": 0.1, "instrumentalness": 0, "liveness": 0.0631, "valence": 0.502, "tempo": 136.054, "artist_name": "LE SSERAFIM", "artist_url": "https://open.spotify.com/artist/4SpbR6yFEvexJuaBpgAU5p", "country": "Saudi Arabia"}]