[{"name": "\u0417\u043d\u0430\u0439\u0434\u0438 \u043c\u0435\u043d\u0435", "popularity": 63, "explicit": false, "ranking": 1, "album_name": "\u0411\u0435\u0440\u0435\u0436\u0438 \u043c\u0435\u043d\u0435", "album_release_date": "2023-09-22", "album_cover": "https://i.scdn.co/image/ab67616d0000b273d247a6006fd67e08e69d8374", "album_url": "https://open.spotify.com/album/7re2czLU735n5zlY6uGRBb", "danceability": 0.759, "energy": 0.464, "key": 7, "mode": 0, "speechiness": 0.0577, "acousticness": 0.712, "instrumentalness": 0.446, "liveness": 0.215, "valence": 0.143, "tempo": 109.974, "artist_name": "Klavdia Petrivna", "artist_url": "https://open.spotify.com/artist/5BwbVAdT6rFF2vGVE8su2y", "country": "Ukraine"}, {"name": "Haunted House", "popularity": 67, "explicit": true, "ranking": 2, "album_name": "AA LANGUAGE 2", "album_release_date": "2023-10-27", "album_cover": "https://i.scdn.co/image/ab67616d0000b273121e4de6551639bc5037324f", "album_url": "https://open.spotify.com/album/7IvfbDBurAnYpUC0w1h1Na", "danceability": 0.905, "energy": 0.726, "key": 8, "mode": 0, "speechiness": 0.0543, "acousticness": 0.0349, "instrumentalness": 0.00963, "liveness": 0.138, "valence": 0.677, "tempo": 150.031, "artist_name": "Aarne", "artist_url": "https://open.spotify.com/artist/5B5qmrbTFvA7TAxWruuwbo", "country": "Ukraine"}, {"name": "\u042f \u0449\u0430\u0441\u043b\u0438\u0432\u0430 - \u041b\u0456\u043a\u0430\u0440\u0456 \u043a\u0430\u0436\u0443\u0442\u044c", "popularity": 61, "explicit": false, "ranking": 3, "album_name": "\u0411\u0435\u0440\u0435\u0436\u0438 \u043c\u0435\u043d\u0435", "album_release_date": "2023-09-22", "album_cover": "https://i.scdn.co/image/ab67616d0000b273d247a6006fd67e08e69d8374", "album_url": "https://open.spotify.com/album/7re2czLU735n5zlY6uGRBb", "danceability": 0.925, "energy": 0.472, "key": 10, "mode": 0, "speechiness": 0.17, "acousticness": 0.747, "instrumentalness": 2.26e-05, "liveness": 0.0897, "valence": 0.705, "tempo": 107.021, "artist_name": "Klavdia Petrivna", "artist_url": "https://open.spotify.com/artist/5BwbVAdT6rFF2vGVE8su2y", "country": "Ukraine"}, {"name": "\u0417\u043d\u0430\u0439\u0434\u0438 \u043c\u0435\u043d\u0435 - KAVA Remix", "popularity": 60, "explicit": false, "ranking": 4, "album_name": "\u0417\u043d\u0430\u0439\u0434\u0438 \u043c\u0435\u043d\u0435 (KAVA Remix)", "album_release_date": "2023-10-15", "album_cover": "https://i.scdn.co/image/ab67616d0000b273c53e7ab136ad7de281b3e268", "album_url": "https://open.spotify.com/album/4TFNfO3cTkY7Ajgzf4cyZM", "danceability": 0.638, "energy": 0.497, "key": 1, "mode": 0, "speechiness": 0.053, "acousticness": 0.425, "instrumentalness": 0.222, "liveness": 0.368, "valence": 0.189, "tempo": 140.085, "artist_name": "Klavdia Petrivna", "artist_url": "https://open.spotify.com/artist/5BwbVAdT6rFF2vGVE8su2y", "country": "Ukraine"}, {"name": "Paint The Town Red", "popularity": 89, "explicit": true, "ranking": 5, "album_name": "Scarlet", "album_release_date": "2023-09-20", "album_cover": "https://i.scdn.co/image/ab67616d0000b273a840032f14ab22da396e43cb", "album_url": "https://open.spotify.com/album/1bBez9PNvkJPW08bU7NYta", "danceability": 0.864, "energy": 0.556, "key": 2, "mode": 0, "speechiness": 0.194, "acousticness": 0.255, "instrumentalness": 3.85e-06, "liveness": 0.112, "valence": 0.726, "tempo": 99.974, "artist_name": "Doja Cat", "artist_url": "https://open.spotify.com/artist/5cj0lLjcoR7YOSnhnX0Po5", "country": "Ukraine"}, {"name": "Strangers", "popularity": 98, "explicit": false, "ranking": 6, "album_name": "Strangers", "album_release_date": "2023-09-01", "album_cover": "https://i.scdn.co/image/ab67616d0000b2734756c2e9ae436437cd75e9f3", "album_url": "https://open.spotify.com/album/18ogtNq9F7DmMkNYO6Xb4k", "danceability": 0.628, "energy": 0.523, "key": 11, "mode": 0, "speechiness": 0.0946, "acousticness": 0.701, "instrumentalness": 0.00274, "liveness": 0.219, "valence": 0.416, "tempo": 169.982, "artist_name": "Kenya Grace", "artist_url": "https://open.spotify.com/artist/7uMDnSZyUYNBPLhPMNuaM2", "country": "Ukraine"}, {"name": "\u0425\u043e\u043b\u043e\u0434", "popularity": 70, "explicit": false, "ranking": 7, "album_name": "\u0425\u043e\u043b\u043e\u0434", "album_release_date": "2023-08-25", "album_cover": "https://i.scdn.co/image/ab67616d0000b273a6d15e69af92525dc13d15e9", "album_url": "https://open.spotify.com/album/2ow8uzDPdwcUgajYFxrylH", "danceability": 0.631, "energy": 0.581, "key": 10, "mode": 0, "speechiness": 0.139, "acousticness": 0.225, "instrumentalness": 0.000495, "liveness": 0.11, "valence": 0.107, "tempo": 94.998, "artist_name": "shadowraze", "artist_url": "https://open.spotify.com/artist/0TO6y1x0LQodwBnxGtQu9o", "country": "Ukraine"}, {"name": "\u0421\u0438\u043b\u0443\u0435\u0442\u0438", "popularity": 63, "explicit": false, "ranking": 8, "album_name": "\u0421\u0438\u043b\u0443\u0435\u0442\u0438", "album_release_date": "2022-10-28", "album_cover": "https://i.scdn.co/image/ab67616d0000b2733ff97da57bb48564dc79b8cd", "album_url": "https://open.spotify.com/album/40R8mdc7vde5T0j3HxlAln", "danceability": 0.527, "energy": 0.861, "key": 8, "mode": 1, "speechiness": 0.0388, "acousticness": 0.0155, "instrumentalness": 0.0311, "liveness": 0.276, "valence": 0.387, "tempo": 77.498, "artist_name": "SadSvit", "artist_url": "https://open.spotify.com/artist/2ojY7fXJxZQhg8Rx5e8h9G", "country": "Ukraine"}, {"name": "4 ur girl", "popularity": 65, "explicit": true, "ranking": 9, "album_name": "AA LANGUAGE 2", "album_release_date": "2023-10-27", "album_cover": "https://i.scdn.co/image/ab67616d0000b273121e4de6551639bc5037324f", "album_url": "https://open.spotify.com/album/7IvfbDBurAnYpUC0w1h1Na", "danceability": 0.839, "energy": 0.745, "key": 3, "mode": 0, "speechiness": 0.139, "acousticness": 0.105, "instrumentalness": 0, "liveness": 0.141, "valence": 0.618, "tempo": 133.968, "artist_name": "Aarne", "artist_url": "https://open.spotify.com/artist/5B5qmrbTFvA7TAxWruuwbo", "country": "Ukraine"}, {"name": "\u0414\u043e\u0434\u043e\u043c\u0443", "popularity": 61, "explicit": false, "ranking": 10, "album_name": "8 \u043c\u0430\u0440\u0430\u0431\u0443", "album_release_date": "2022-12-16", "album_cover": "https://i.scdn.co/image/ab67616d0000b2730af07d4c10ffdae04e3049ee", "album_url": "https://open.spotify.com/album/2Q0kX7go1YkwNVix8e1Chw", "danceability": 0.72, "energy": 0.674, "key": 7, "mode": 0, "speechiness": 0.0828, "acousticness": 0.125, "instrumentalness": 0.00258, "liveness": 0.0928, "valence": 0.219, "tempo": 76.617, "artist_name": "Wellboy", "artist_url": "https://open.spotify.com/artist/6l5IEx62Nsc2k1QyfaWvEz", "country": "Ukraine"}, {"name": "\u041a\u043e\u0445\u0430\u044e, \u0430\u043b\u0435 \u043d\u0435 \u0437\u043e\u0432\u0441\u0456\u043c", "popularity": 61, "explicit": false, "ranking": 11, "album_name": "\u041a\u043e\u0445\u0430\u044e, \u0430\u043b\u0435 \u043d\u0435 \u0437\u043e\u0432\u0441\u0456\u043c", "album_release_date": "2023-06-21", "album_cover": "https://i.scdn.co/image/ab67616d0000b273c918d5da6d911927f7e6d11b", "album_url": "https://open.spotify.com/album/5cnpwmYQBU8JgK8AYYUsFS", "danceability": 0.873, "energy": 0.616, "key": 0, "mode": 0, "speechiness": 0.11, "acousticness": 0.0487, "instrumentalness": 0, "liveness": 0.159, "valence": 0.542, "tempo": 130.13, "artist_name": "DOROFEEVA", "artist_url": "https://open.spotify.com/artist/7wl1m5vgWkCP3cqYVj2noM", "country": "Ukraine"}, {"name": "greedy", "popularity": 100, "explicit": true, "ranking": 12, "album_name": "greedy", "album_release_date": "2023-09-15", "album_cover": "https://i.scdn.co/image/ab67616d0000b27322fd802bc61db666c7c81aa8", "album_url": "https://open.spotify.com/album/3UOV8XvCwMKaATRNXrYCjN", "danceability": 0.75, "energy": 0.733, "key": 6, "mode": 0, "speechiness": 0.0319, "acousticness": 0.256, "instrumentalness": 0, "liveness": 0.114, "valence": 0.844, "tempo": 111.018, "artist_name": "Tate McRae", "artist_url": "https://open.spotify.com/artist/45dkTj5sMRSjrmBSBeiHym", "country": "Ukraine"}, {"name": "\u041f\u043e\u0440\u0456\u0447\u043a\u0430", "popularity": 60, "explicit": false, "ranking": 13, "album_name": "\u041f\u043e\u0440\u0456\u0447\u043a\u0430", "album_release_date": "2023-04-05", "album_cover": "https://i.scdn.co/image/ab67616d0000b273a4a010f0769a2dbd9f21c32b", "album_url": "https://open.spotify.com/album/7psQf9ptuKCMeDfvlumlmU", "danceability": 0.747, "energy": 0.711, "key": 11, "mode": 0, "speechiness": 0.0645, "acousticness": 0.348, "instrumentalness": 0, "liveness": 0.311, "valence": 0.766, "tempo": 125.487, "artist_name": "YAKTAK", "artist_url": "https://open.spotify.com/artist/5zjgy7grnZbt2L12meuxog", "country": "Ukraine"}, {"name": "\u041f\u043e\u0433\u043b\u044f\u0434", "popularity": 61, "explicit": false, "ranking": 14, "album_name": "\u041f\u043e\u0433\u043b\u044f\u0434", "album_release_date": "2022-10-13", "album_cover": "https://i.scdn.co/image/ab67616d0000b273e8b0186116bb1d2224f2002f", "album_url": "https://open.spotify.com/album/2U3ecGQPqMwXz4vSOps8Td", "danceability": 0.761, "energy": 0.793, "key": 9, "mode": 0, "speechiness": 0.0469, "acousticness": 0.0908, "instrumentalness": 6.68e-06, "liveness": 0.566, "valence": 0.548, "tempo": 110.043, "artist_name": "YAKTAK", "artist_url": "https://open.spotify.com/artist/5zjgy7grnZbt2L12meuxog", "country": "Ukraine"}, {"name": "SPIT IN MY FACE!", "popularity": 86, "explicit": true, "ranking": 15, "album_name": "SPIT IN MY FACE!", "album_release_date": "2022-12-20", "album_cover": "https://i.scdn.co/image/ab67616d0000b27360ddc59c8d590a37cf2348f3", "album_url": "https://open.spotify.com/album/2XurGuugADHAwF8gEYjtMA", "danceability": 0.73, "energy": 0.785, "key": 8, "mode": 1, "speechiness": 0.0554, "acousticness": 0.0464, "instrumentalness": 0.0216, "liveness": 0.111, "valence": 0.649, "tempo": 94.094, "artist_name": "ThxSoMch", "artist_url": "https://open.spotify.com/artist/4MvZhE1iuzttcoyepkpfdF", "country": "Ukraine"}, {"name": "\u041c\u043e\u043b\u0447\u0430\u0442\u044c", "popularity": 63, "explicit": false, "ranking": 16, "album_name": "AA LANGUAGE 2", "album_release_date": "2023-10-27", "album_cover": "https://i.scdn.co/image/ab67616d0000b273121e4de6551639bc5037324f", "album_url": "https://open.spotify.com/album/7IvfbDBurAnYpUC0w1h1Na", "danceability": 0.654, "energy": 0.658, "key": 7, "mode": 0, "speechiness": 0.346, "acousticness": 0.102, "instrumentalness": 0.00282, "liveness": 0.103, "valence": 0.638, "tempo": 150.046, "artist_name": "Aarne", "artist_url": "https://open.spotify.com/artist/5B5qmrbTFvA7TAxWruuwbo", "country": "Ukraine"}, {"name": "Daylight", "popularity": 95, "explicit": false, "ranking": 17, "album_name": "Daylight", "album_release_date": "2023-04-14", "album_cover": "https://i.scdn.co/image/ab67616d0000b27395ca6a9b4083a86c149934ae", "album_url": "https://open.spotify.com/album/6NcI39WPu4kY6Tul11nhSv", "danceability": 0.508, "energy": 0.43, "key": 2, "mode": 0, "speechiness": 0.0335, "acousticness": 0.83, "instrumentalness": 0.000441, "liveness": 0.093, "valence": 0.324, "tempo": 130.09, "artist_name": "David Kushner", "artist_url": "https://open.spotify.com/artist/33NVpKoXjItPwUJTMZIOiY", "country": "Ukraine"}, {"name": "\u041d\u0435 \u0432\u0442\u0440\u0430\u0442\u0438\u043c\u043e \u0437\u0432'\u044f\u0437\u043e\u043a", "popularity": 59, "explicit": false, "ranking": 18, "album_name": "\u041d\u0435 \u0432\u0442\u0440\u0430\u0442\u0438\u043c\u043e \u0437\u0432'\u044f\u0437\u043e\u043a", "album_release_date": "2023-04-13", "album_cover": "https://i.scdn.co/image/ab67616d0000b273bf63d184b6ac740d48393da1", "album_url": "https://open.spotify.com/album/67H8Ds24jGQTAfqzdc3xpX", "danceability": 0.793, "energy": 0.707, "key": 9, "mode": 0, "speechiness": 0.12, "acousticness": 0.328, "instrumentalness": 0, "liveness": 0.0872, "valence": 0.561, "tempo": 81.977, "artist_name": "alyona alyona", "artist_url": "https://open.spotify.com/artist/2ic3GGGmkixOZP4qnakSA8", "country": "Ukraine"}, {"name": "\u0425\u0442\u043e \u0442\u0438", "popularity": 59, "explicit": false, "ranking": 19, "album_name": "\u0411\u0435\u0440\u0435\u0436\u0438 \u043c\u0435\u043d\u0435", "album_release_date": "2023-09-22", "album_cover": "https://i.scdn.co/image/ab67616d0000b273d247a6006fd67e08e69d8374", "album_url": "https://open.spotify.com/album/7re2czLU735n5zlY6uGRBb", "danceability": 0.89, "energy": 0.447, "key": 2, "mode": 0, "speechiness": 0.0385, "acousticness": 0.339, "instrumentalness": 6.6e-06, "liveness": 0.139, "valence": 0.803, "tempo": 109.991, "artist_name": "Klavdia Petrivna", "artist_url": "https://open.spotify.com/artist/5BwbVAdT6rFF2vGVE8su2y", "country": "Ukraine"}, {"name": "\u0417\u0438\u043c\u0430 \u0432 \u0441\u0435\u0440\u0434\u0446\u0435", "popularity": 58, "explicit": false, "ranking": 20, "album_name": "\u0418\u0437 \u0446\u0432\u0435\u0442\u043e\u0432 \u0438 \u0442\u0435\u043c\u043d\u043e\u0442\u044b", "album_release_date": "2022-12-16", "album_cover": "https://i.scdn.co/image/ab67616d0000b273abcab15ddf0f58bfea7b1a6d", "album_url": "https://open.spotify.com/album/5Psqb8umHXgLiEXpkAsYl4", "danceability": 0.66, "energy": 0.763, "key": 5, "mode": 0, "speechiness": 0.0351, "acousticness": 0.107, "instrumentalness": 0, "liveness": 0.229, "valence": 0.61, "tempo": 108.054, "artist_name": "Moya Mishel", "artist_url": "https://open.spotify.com/artist/28oFVU5sNejm6p76RkSwtQ", "country": "Ukraine"}, {"name": "\u0411\u0443\u0440\u0435\u0432\u0456\u044f\u043c\u0438", "popularity": 59, "explicit": false, "ranking": 21, "album_name": "\u0411\u0443\u0440\u0435\u0432\u0456\u044f\u043c\u0438", "album_release_date": "2023-04-17", "album_cover": "https://i.scdn.co/image/ab67616d0000b273abaa01e8b144a02060f1873e", "album_url": "https://open.spotify.com/album/7xOUWVVIMccfuLyUskG9eX", "danceability": 0.698, "energy": 0.51, "key": 5, "mode": 0, "speechiness": 0.0423, "acousticness": 0.464, "instrumentalness": 0, "liveness": 0.107, "valence": 0.4, "tempo": 129.979, "artist_name": "SHUMEI", "artist_url": "https://open.spotify.com/artist/1BtGSVQey2HyYbFiw8O1mz", "country": "Ukraine"}, {"name": "9mm", "popularity": 15, "explicit": true, "ranking": 22, "album_name": "Memphis Cult Vol. 6", "album_release_date": "2023-02-23", "album_cover": "https://i.scdn.co/image/ab67616d0000b2733818d94e3353a92945780d9c", "album_url": "https://open.spotify.com/album/5CZnhiTI3K85wLKwPLNOJB", "danceability": 0.737, "energy": 0.915, "key": 0, "mode": 1, "speechiness": 0.0412, "acousticness": 0.00322, "instrumentalness": 2.58e-05, "liveness": 0.084, "valence": 0.304, "tempo": 154.964, "artist_name": "Memphis Cult", "artist_url": "https://open.spotify.com/artist/6n9sdNb7mWvVmARDT6ujnJ", "country": "Ukraine"}, {"name": "Automotivo Bibi Fogosa", "popularity": 89, "explicit": true, "ranking": 23, "album_name": "Automotivo Bibi Fogosa", "album_release_date": "2023-05-19", "album_cover": "https://i.scdn.co/image/ab67616d0000b273530b46efc7157d71389648f2", "album_url": "https://open.spotify.com/album/0Hj2X0CQBjpWapFzNQGbk2", "danceability": 0.726, "energy": 0.873, "key": 9, "mode": 1, "speechiness": 0.0266, "acousticness": 0.2, "instrumentalness": 1.71e-06, "liveness": 0.0953, "valence": 0.725, "tempo": 135.052, "artist_name": "Bibi Babydoll", "artist_url": "https://open.spotify.com/artist/6R26kGib2ubbZJMh7kKVGV", "country": "Ukraine"}, {"name": "\u0429\u043e\u0431 \u043d\u0435 \u0431\u0443\u043b\u043e", "popularity": 59, "explicit": false, "ranking": 24, "album_name": "\u0429\u043e\u0431 \u043d\u0435 \u0431\u0443\u043b\u043e", "album_release_date": "2022-12-08", "album_cover": "https://i.scdn.co/image/ab67616d0000b273ff60ecc8c1da1badeb903b40", "album_url": "https://open.spotify.com/album/00hex8Oa9MjhX3IVjj81sb", "danceability": 0.869, "energy": 0.456, "key": 11, "mode": 0, "speechiness": 0.497, "acousticness": 0.681, "instrumentalness": 0, "liveness": 0.0698, "valence": 0.381, "tempo": 114.136, "artist_name": "DOROFEEVA", "artist_url": "https://open.spotify.com/artist/7wl1m5vgWkCP3cqYVj2noM", "country": "Ukraine"}, {"name": "METAMORPHOSIS", "popularity": 88, "explicit": true, "ranking": 25, "album_name": "METAMORPHOSIS", "album_release_date": "2021-11-25", "album_cover": "https://i.scdn.co/image/ab67616d0000b273b852a616ae3a49a1f6b0f16e", "album_url": "https://open.spotify.com/album/3apQZbgVql9mHJlp43jk5D", "danceability": 0.593, "energy": 0.641, "key": 7, "mode": 0, "speechiness": 0.0992, "acousticness": 0.426, "instrumentalness": 0.901, "liveness": 0.122, "valence": 0.147, "tempo": 175.014, "artist_name": "INTERWORLD", "artist_url": "https://open.spotify.com/artist/5hKGLu4Ik88FzWcTPhWNTN", "country": "Ukraine"}, {"name": "\u0421\u043f\u0430\u043b\u0430\u0445\u0438", "popularity": 58, "explicit": false, "ranking": 26, "album_name": "\u0421\u043f\u0430\u043b\u0430\u0445\u0438", "album_release_date": "2023-05-19", "album_cover": "https://i.scdn.co/image/ab67616d0000b2732a6c689aa028cf3092e113da", "album_url": "https://open.spotify.com/album/4DgFv3Bs9zX3QhK7iaKD1d", "danceability": 0.753, "energy": 0.836, "key": 6, "mode": 0, "speechiness": 0.1, "acousticness": 0.0403, "instrumentalness": 0.000123, "liveness": 0.0329, "valence": 0.819, "tempo": 99.969, "artist_name": "POSITIFF", "artist_url": "https://open.spotify.com/artist/3f7zhsCueKsjZbwOkoTsME", "country": "Ukraine"}, {"name": "IT GIRL", "popularity": 84, "explicit": true, "ranking": 27, "album_name": "IT GIRL", "album_release_date": "2023-09-30", "album_cover": "https://i.scdn.co/image/ab67616d0000b2736a103a46444f5fbf948b8027", "album_url": "https://open.spotify.com/album/6Dbkq4a0KggLhGxxt8p1lH", "danceability": 0.969, "energy": 0.707, "key": 1, "mode": 1, "speechiness": 0.258, "acousticness": 0.00822, "instrumentalness": 0, "liveness": 0.314, "valence": 0.421, "tempo": 124.991, "artist_name": "Aliyah's Interlude", "artist_url": "https://open.spotify.com/artist/7maQENQfaF8xDdEJp4i545", "country": "Ukraine"}, {"name": "\u0423\u043d\u043e\u0447\u0456", "popularity": 59, "explicit": false, "ranking": 28, "album_name": "\u0423\u043d\u043e\u0447\u0456", "album_release_date": "2023-08-17", "album_cover": "https://i.scdn.co/image/ab67616d0000b2735f6c5f25597a74b485359dfa", "album_url": "https://open.spotify.com/album/24bc8MBCroFdDuLDyVJfVS", "danceability": 0.674, "energy": 0.659, "key": 8, "mode": 0, "speechiness": 0.0338, "acousticness": 0.259, "instrumentalness": 0, "liveness": 0.329, "valence": 0.324, "tempo": 150.075, "artist_name": "YAKTAK", "artist_url": "https://open.spotify.com/artist/5zjgy7grnZbt2L12meuxog", "country": "Ukraine"}, {"name": "\u0428\u0443\u043a\u0430\u0432 \u0442\u0435\u0431\u0435. \u0417\u043d\u0430\u0439\u0448\u043e\u0432 \u0442\u0435\u0431\u0435", "popularity": 59, "explicit": false, "ranking": 29, "album_name": "\u0428\u0443\u043a\u0430\u0432 \u0442\u0435\u0431\u0435. \u0417\u043d\u0430\u0439\u0448\u043e\u0432 \u0442\u0435\u0431\u0435", "album_release_date": "2021-07-30", "album_cover": "https://i.scdn.co/image/ab67616d0000b27347ab84244ba4bc7582238684", "album_url": "https://open.spotify.com/album/0eUaHLgfMJjmgIjhvktlaz", "danceability": 0.711, "energy": 0.6, "key": 0, "mode": 1, "speechiness": 0.141, "acousticness": 0.419, "instrumentalness": 1.33e-06, "liveness": 0.0843, "valence": 0.201, "tempo": 112.126, "artist_name": "VovaZiLvova", "artist_url": "https://open.spotify.com/artist/7MFvm8pwjLdmVBZddGNiQH", "country": "Ukraine"}, {"name": "\u041a\u0440\u0435\u043f\u0447\u0435", "popularity": 65, "explicit": false, "ranking": 30, "album_name": "\u041a\u0440\u0435\u043f\u0447\u0435", "album_release_date": "2016-01-05", "album_cover": "https://i.scdn.co/image/ab67616d0000b273afbfd20e80e86fe041aca78f", "album_url": "https://open.spotify.com/album/1e82MHQz8mczZXotjeR0ky", "danceability": 0.769, "energy": 0.31, "key": 9, "mode": 0, "speechiness": 0.372, "acousticness": 0.872, "instrumentalness": 0, "liveness": 0.144, "valence": 0.71, "tempo": 77.994, "artist_name": "KRBK", "artist_url": "https://open.spotify.com/artist/0E56Ncr2I37JQhW71UJALE", "country": "Ukraine"}, {"name": "Seven (feat. Latto) (Explicit Ver.)", "popularity": 97, "explicit": true, "ranking": 31, "album_name": "Seven (feat. Latto)", "album_release_date": "2023-07-14", "album_cover": "https://i.scdn.co/image/ab67616d0000b273bf5cce5a0e1ed03a626bdd74", "album_url": "https://open.spotify.com/album/53985D8g3JcGBoULSOYYKX", "danceability": 0.802, "energy": 0.832, "key": 11, "mode": 1, "speechiness": 0.0434, "acousticness": 0.311, "instrumentalness": 0, "liveness": 0.0815, "valence": 0.89, "tempo": 124.997, "artist_name": "Jung Kook", "artist_url": "https://open.spotify.com/artist/6HaGTQPmzraVmaVxvz6EUc", "country": "Ukraine"}, {"name": "\u0425\u043e\u0447\u0435\u0448", "popularity": 58, "explicit": false, "ranking": 32, "album_name": "\u0425\u043e\u0447\u0435\u0448", "album_release_date": "2023-03-28", "album_cover": "https://i.scdn.co/image/ab67616d0000b273de6f183185fdd81458e3bbf3", "album_url": "https://open.spotify.com/album/2rJgsuytbx0DNv1ngQ2w6I", "danceability": 0.588, "energy": 0.593, "key": 11, "mode": 0, "speechiness": 0.0382, "acousticness": 0.0897, "instrumentalness": 0.000591, "liveness": 0.112, "valence": 0.263, "tempo": 147.953, "artist_name": "\u041f\u0456\u0441\u043b\u044f \u0414\u043e\u0449\u0443", "artist_url": "https://open.spotify.com/artist/7vUQFioWvCavqy0WKpo1yD", "country": "Ukraine"}, {"name": "\u041d\u0435\u0431\u043e \u0445\u0438\u043b\u0438\u0442\u044c\u0441\u044f", "popularity": 58, "explicit": false, "ranking": 33, "album_name": "\u041d\u0435\u0431\u043e \u0445\u0438\u043b\u0438\u0442\u044c\u0441\u044f", "album_release_date": "2023-06-15", "album_cover": "https://i.scdn.co/image/ab67616d0000b2735c29834a8ee184bb48f9c4e5", "album_url": "https://open.spotify.com/album/6SoyCHcNPVDIPpojssKObm", "danceability": 0.827, "energy": 0.613, "key": 1, "mode": 1, "speechiness": 0.0484, "acousticness": 0.196, "instrumentalness": 0, "liveness": 0.0891, "valence": 0.634, "tempo": 130.098, "artist_name": "alyona alyona", "artist_url": "https://open.spotify.com/artist/2ic3GGGmkixOZP4qnakSA8", "country": "Ukraine"}, {"name": "LOVELY BASTARDS", "popularity": 88, "explicit": true, "ranking": 34, "album_name": "LOVELY BASTARDS", "album_release_date": "2023-08-25", "album_cover": "https://i.scdn.co/image/ab67616d0000b273226383907a53ab4c13cca8e2", "album_url": "https://open.spotify.com/album/2b3Kiolsu42XiVvhRmTEsM", "danceability": 0.613, "energy": 0.81, "key": 1, "mode": 1, "speechiness": 0.488, "acousticness": 0.832, "instrumentalness": 0.899, "liveness": 0.137, "valence": 0.686, "tempo": 150.251, "artist_name": "ZWE1HVNDXR", "artist_url": "https://open.spotify.com/artist/33rnQWadiG2aauIwIxPxfB", "country": "Ukraine"}, {"name": "ecstacy (slowed)", "popularity": 90, "explicit": true, "ranking": 35, "album_name": "ecstacy (slowed)", "album_release_date": "2023-06-06", "album_cover": "https://i.scdn.co/image/ab67616d0000b273cddfe70492c57a78e4d86b1c", "album_url": "https://open.spotify.com/album/6KLSjdqyjISLUhW8bx0Bqi", "danceability": 0.551, "energy": 0.677, "key": 2, "mode": 1, "speechiness": 0.0665, "acousticness": 0.0173, "instrumentalness": 0, "liveness": 0.381, "valence": 0.195, "tempo": 106.414, "artist_name": "SUICIDAL-IDOL", "artist_url": "https://open.spotify.com/artist/6KOszWgIriJLaPOySuBOTI", "country": "Ukraine"}, {"name": "\u0412\u0456\u0434\u0440\u0438\u0432\u0430\u044e\u0447\u0438\u0441\u044c", "popularity": 59, "explicit": false, "ranking": 36, "album_name": "\u0412\u0456\u0434\u0440\u0438\u0432\u0430\u044e\u0447\u0438\u0441\u044c", "album_release_date": "2023-05-03", "album_cover": "https://i.scdn.co/image/ab67616d0000b2730e2856c6527bc8c06af99c62", "album_url": "https://open.spotify.com/album/2nUr5oj4NmZsvTK6u3ug3g", "danceability": 0.691, "energy": 0.68, "key": 9, "mode": 0, "speechiness": 0.0426, "acousticness": 0.53, "instrumentalness": 0, "liveness": 0.102, "valence": 0.546, "tempo": 125.033, "artist_name": "Parfeniuk", "artist_url": "https://open.spotify.com/artist/64XGTiElvPUfmJjyWJnW8C", "country": "Ukraine"}, {"name": "\u041a\u0430\u0441\u0435\u0442\u0430", "popularity": 60, "explicit": false, "ranking": 37, "album_name": "Cassette", "album_release_date": "2021-12-13", "album_cover": "https://i.scdn.co/image/ab67616d0000b273b8743497661aee8c8bc522c5", "album_url": "https://open.spotify.com/album/0Wn5sHYtC7vPPX0n2AVJmF", "danceability": 0.654, "energy": 0.743, "key": 10, "mode": 0, "speechiness": 0.0315, "acousticness": 0.294, "instrumentalness": 0.0495, "liveness": 0.109, "valence": 0.632, "tempo": 169.98, "artist_name": "SadSvit", "artist_url": "https://open.spotify.com/artist/2ojY7fXJxZQhg8Rx5e8h9G", "country": "Ukraine"}, {"name": "\u041c\u0435\u0447\u0442\u044b", "popularity": 62, "explicit": true, "ranking": 38, "album_name": "AA LANGUAGE 2", "album_release_date": "2023-10-27", "album_cover": "https://i.scdn.co/image/ab67616d0000b273121e4de6551639bc5037324f", "album_url": "https://open.spotify.com/album/7IvfbDBurAnYpUC0w1h1Na", "danceability": 0.945, "energy": 0.641, "key": 6, "mode": 0, "speechiness": 0.179, "acousticness": 0.419, "instrumentalness": 0, "liveness": 0.0962, "valence": 0.789, "tempo": 123.99, "artist_name": "Aarne", "artist_url": "https://open.spotify.com/artist/5B5qmrbTFvA7TAxWruuwbo", "country": "Ukraine"}, {"name": "\u0422\u0440\u0435\u0437\u0432\u043e", "popularity": 62, "explicit": false, "ranking": 39, "album_name": "AA LANGUAGE 2", "album_release_date": "2023-10-27", "album_cover": "https://i.scdn.co/image/ab67616d0000b273121e4de6551639bc5037324f", "album_url": "https://open.spotify.com/album/7IvfbDBurAnYpUC0w1h1Na", "danceability": 0.82, "energy": 0.676, "key": 5, "mode": 1, "speechiness": 0.102, "acousticness": 0.36, "instrumentalness": 0, "liveness": 0.101, "valence": 0.465, "tempo": 86.978, "artist_name": "Aarne", "artist_url": "https://open.spotify.com/artist/5B5qmrbTFvA7TAxWruuwbo", "country": "Ukraine"}, {"name": "I Wanna Be Yours", "popularity": 95, "explicit": false, "ranking": 40, "album_name": "AM", "album_release_date": "2013-09-09", "album_cover": "https://i.scdn.co/image/ab67616d0000b2734ae1c4c5c45aabe565499163", "album_url": "https://open.spotify.com/album/78bpIziExqiI9qztvNFlQu", "danceability": 0.464, "energy": 0.417, "key": 0, "mode": 0, "speechiness": 0.0256, "acousticness": 0.136, "instrumentalness": 0.022, "liveness": 0.0974, "valence": 0.479, "tempo": 67.528, "artist_name": "Arctic Monkeys", "artist_url": "https://open.spotify.com/artist/7Ln80lUS6He07XvHI8qqHH", "country": "Ukraine"}, {"name": "\u0406\u043c\u043f\u0435\u0440\u0430\u0442\u043e\u0440\u0438", "popularity": 57, "explicit": true, "ranking": 41, "album_name": "\u0406\u043c\u043f\u0435\u0440\u0430\u0442\u043e\u0440\u0438", "album_release_date": "2023-10-13", "album_cover": "https://i.scdn.co/image/ab67616d0000b2730282a72c159290edc4b8430b", "album_url": "https://open.spotify.com/album/0JBZLbhsqALewaXVmlPmsG", "danceability": 0.84, "energy": 0.439, "key": 2, "mode": 0, "speechiness": 0.275, "acousticness": 0.919, "instrumentalness": 0.0411, "liveness": 0.136, "valence": 0.483, "tempo": 130.016, "artist_name": "Klavdia Petrivna", "artist_url": "https://open.spotify.com/artist/5BwbVAdT6rFF2vGVE8su2y", "country": "Ukraine"}, {"name": "IDGAF (feat. Yeat)", "popularity": 94, "explicit": true, "ranking": 42, "album_name": "For All The Dogs", "album_release_date": "2023-10-06", "album_cover": "https://i.scdn.co/image/ab67616d0000b2737d384516b23347e92a587ed1", "album_url": "https://open.spotify.com/album/4czdORdCWP9umpbhFXK2fW", "danceability": 0.663, "energy": 0.67, "key": 8, "mode": 1, "speechiness": 0.271, "acousticness": 0.0464, "instrumentalness": 8.92e-05, "liveness": 0.205, "valence": 0.138, "tempo": 136.952, "artist_name": "Drake", "artist_url": "https://open.spotify.com/artist/3TVXtAsR1Inumwj472S9r4", "country": "Ukraine"}, {"name": "Sweater Weather", "popularity": 93, "explicit": false, "ranking": 43, "album_name": "I Love You.", "album_release_date": "2013-04-19", "album_cover": "https://i.scdn.co/image/ab67616d0000b2738265a736a1eb838ad5a0b921", "album_url": "https://open.spotify.com/album/4xkM0BwLM9H2IUcbYzpcBI", "danceability": 0.612, "energy": 0.807, "key": 10, "mode": 1, "speechiness": 0.0336, "acousticness": 0.0495, "instrumentalness": 0.0177, "liveness": 0.101, "valence": 0.398, "tempo": 124.053, "artist_name": "The Neighbourhood", "artist_url": "https://open.spotify.com/artist/77SW9BnxLY8rJ0RciFqkHh", "country": "Ukraine"}, {"name": "MONTAGEM - PR FUNK", "popularity": 88, "explicit": false, "ranking": 44, "album_name": "MONTAGEM - PR FUNK", "album_release_date": "2023-05-01", "album_cover": "https://i.scdn.co/image/ab67616d0000b2736a922a01d3fb1c53873b1f9d", "album_url": "https://open.spotify.com/album/2HuMAoXpr6HDryNHipbCpB", "danceability": 0.877, "energy": 0.803, "key": 9, "mode": 1, "speechiness": 0.0507, "acousticness": 0.734, "instrumentalness": 0.056, "liveness": 0.087, "valence": 0.795, "tempo": 130.028, "artist_name": "S3BZS", "artist_url": "https://open.spotify.com/artist/6zFMFB1JvNHkHvCSudF4id", "country": "Ukraine"}, {"name": "\u0414\u043e\u043b\u043e\u043d\u0456", "popularity": 57, "explicit": false, "ranking": 45, "album_name": "\u0414\u043e\u043b\u043e\u043d\u0456", "album_release_date": "2023-06-22", "album_cover": "https://i.scdn.co/image/ab67616d0000b273e281f084200c5292c12269d2", "album_url": "https://open.spotify.com/album/3NmrYQxt3SIQg22hmZvxOq", "danceability": 0.761, "energy": 0.59, "key": 10, "mode": 1, "speechiness": 0.0339, "acousticness": 0.171, "instrumentalness": 0, "liveness": 0.122, "valence": 0.732, "tempo": 113.997, "artist_name": "Parfeniuk", "artist_url": "https://open.spotify.com/artist/64XGTiElvPUfmJjyWJnW8C", "country": "Ukraine"}, {"name": "\u0412\u0430\u043c\u043f\u0438\u0440", "popularity": 66, "explicit": true, "ranking": 46, "album_name": "\u0412\u0430\u043c\u043f\u0438\u0440", "album_release_date": "2023-10-06", "album_cover": "https://i.scdn.co/image/ab67616d0000b273d9e9f6bef616dbb818185bef", "album_url": "https://open.spotify.com/album/5lBcoU3iDbQsfnS7Ik6OXb", "danceability": 0.694, "energy": 0.544, "key": 9, "mode": 0, "speechiness": 0.0377, "acousticness": 0.126, "instrumentalness": 0, "liveness": 0.579, "valence": 0.569, "tempo": 140.096, "artist_name": "Scally Milano", "artist_url": "https://open.spotify.com/artist/1nnaE1FllcW0TlDdPVmdPg", "country": "Ukraine"}, {"name": "\u0422\u0430\u043c \u0433\u0434\u0435 \u044f", "popularity": 62, "explicit": true, "ranking": 47, "album_name": "AA LANGUAGE 2", "album_release_date": "2023-10-27", "album_cover": "https://i.scdn.co/image/ab67616d0000b273121e4de6551639bc5037324f", "album_url": "https://open.spotify.com/album/7IvfbDBurAnYpUC0w1h1Na", "danceability": 0.781, "energy": 0.743, "key": 1, "mode": 1, "speechiness": 0.307, "acousticness": 0.0794, "instrumentalness": 1.14e-06, "liveness": 0.0674, "valence": 0.472, "tempo": 166.043, "artist_name": "Aarne", "artist_url": "https://open.spotify.com/artist/5B5qmrbTFvA7TAxWruuwbo", "country": "Ukraine"}, {"name": "ice ice ice", "popularity": 62, "explicit": true, "ranking": 48, "album_name": "AA LANGUAGE 2", "album_release_date": "2023-10-27", "album_cover": "https://i.scdn.co/image/ab67616d0000b273121e4de6551639bc5037324f", "album_url": "https://open.spotify.com/album/7IvfbDBurAnYpUC0w1h1Na", "danceability": 0.701, "energy": 0.868, "key": 8, "mode": 1, "speechiness": 0.0768, "acousticness": 0.00353, "instrumentalness": 1.14e-05, "liveness": 0.332, "valence": 0.536, "tempo": 168.017, "artist_name": "Aarne", "artist_url": "https://open.spotify.com/artist/5B5qmrbTFvA7TAxWruuwbo", "country": "Ukraine"}, {"name": "Full House", "popularity": 61, "explicit": true, "ranking": 49, "album_name": "AA LANGUAGE 2", "album_release_date": "2023-10-27", "album_cover": "https://i.scdn.co/image/ab67616d0000b273121e4de6551639bc5037324f", "album_url": "https://open.spotify.com/album/7IvfbDBurAnYpUC0w1h1Na", "danceability": 0.872, "energy": 0.748, "key": 1, "mode": 1, "speechiness": 0.0807, "acousticness": 0.121, "instrumentalness": 0.000263, "liveness": 0.163, "valence": 0.403, "tempo": 123.032, "artist_name": "Aarne", "artist_url": "https://open.spotify.com/artist/5B5qmrbTFvA7TAxWruuwbo", "country": "Ukraine"}, {"name": "\u0426\u0430\u0440\u0438\u0446\u0430", "popularity": 62, "explicit": false, "ranking": 50, "album_name": "\u0426\u0430\u0440\u0438\u0446\u0430", "album_release_date": "2023-09-29", "album_cover": "https://i.scdn.co/image/ab67616d0000b273c6f1ade459affcb42a10077e", "album_url": "https://open.spotify.com/album/2rnuTMnUTPZOZQUw99TleP", "danceability": 0.734, "energy": 0.813, "key": 5, "mode": 0, "speechiness": 0.0463, "acousticness": 0.105, "instrumentalness": 0, "liveness": 0.354, "valence": 0.511, "tempo": 116.007, "artist_name": "ANNA ASTI", "artist_url": "https://open.spotify.com/artist/40YXr3tdSqFv0kfmgjj8vP", "country": "Ukraine"}]