[{"name": "Strangers", "popularity": 98, "explicit": false, "ranking": 1, "album_name": "Strangers", "album_release_date": "2023-09-01", "album_cover": "https://i.scdn.co/image/ab67616d0000b2734756c2e9ae436437cd75e9f3", "album_url": "https://open.spotify.com/album/18ogtNq9F7DmMkNYO6Xb4k", "danceability": 0.628, "energy": 0.523, "key": 11, "mode": 0, "speechiness": 0.0946, "acousticness": 0.701, "instrumentalness": 0.00274, "liveness": 0.219, "valence": 0.416, "tempo": 169.982, "artist_name": "Kenya Grace", "artist_url": "https://open.spotify.com/artist/7uMDnSZyUYNBPLhPMNuaM2", "country": "Latvia"}, {"name": "greedy", "popularity": 100, "explicit": true, "ranking": 2, "album_name": "greedy", "album_release_date": "2023-09-15", "album_cover": "https://i.scdn.co/image/ab67616d0000b27322fd802bc61db666c7c81aa8", "album_url": "https://open.spotify.com/album/3UOV8XvCwMKaATRNXrYCjN", "danceability": 0.75, "energy": 0.733, "key": 6, "mode": 0, "speechiness": 0.0319, "acousticness": 0.256, "instrumentalness": 0, "liveness": 0.114, "valence": 0.844, "tempo": 111.018, "artist_name": "Tate McRae", "artist_url": "https://open.spotify.com/artist/45dkTj5sMRSjrmBSBeiHym", "country": "Latvia"}, {"name": "Paint The Town Red", "popularity": 89, "explicit": true, "ranking": 3, "album_name": "Scarlet", "album_release_date": "2023-09-20", "album_cover": "https://i.scdn.co/image/ab67616d0000b273a840032f14ab22da396e43cb", "album_url": "https://open.spotify.com/album/1bBez9PNvkJPW08bU7NYta", "danceability": 0.864, "energy": 0.556, "key": 2, "mode": 0, "speechiness": 0.194, "acousticness": 0.255, "instrumentalness": 3.85e-06, "liveness": 0.112, "valence": 0.726, "tempo": 99.974, "artist_name": "Doja Cat", "artist_url": "https://open.spotify.com/artist/5cj0lLjcoR7YOSnhnX0Po5", "country": "Latvia"}, {"name": "Prada", "popularity": 94, "explicit": true, "ranking": 4, "album_name": "Prada", "album_release_date": "2023-08-11", "album_cover": "https://i.scdn.co/image/ab67616d0000b273e4b7dccdfd54375ded9ccc5c", "album_url": "https://open.spotify.com/album/5MU0RmBSpoSxOPYBfcobDc", "danceability": 0.638, "energy": 0.717, "key": 8, "mode": 1, "speechiness": 0.0375, "acousticness": 0.001, "instrumentalness": 1.79e-06, "liveness": 0.113, "valence": 0.422, "tempo": 141.904, "artist_name": "cass\u00f6", "artist_url": "https://open.spotify.com/artist/5wCmhq5J2hPwL2r0eKurxn", "country": "Latvia"}, {"name": "IDGAF (feat. Yeat)", "popularity": 94, "explicit": true, "ranking": 5, "album_name": "For All The Dogs", "album_release_date": "2023-10-06", "album_cover": "https://i.scdn.co/image/ab67616d0000b2737d384516b23347e92a587ed1", "album_url": "https://open.spotify.com/album/4czdORdCWP9umpbhFXK2fW", "danceability": 0.663, "energy": 0.67, "key": 8, "mode": 1, "speechiness": 0.271, "acousticness": 0.0464, "instrumentalness": 8.92e-05, "liveness": 0.205, "valence": 0.138, "tempo": 136.952, "artist_name": "Drake", "artist_url": "https://open.spotify.com/artist/3TVXtAsR1Inumwj472S9r4", "country": "Latvia"}, {"name": "Daylight", "popularity": 95, "explicit": false, "ranking": 6, "album_name": "Daylight", "album_release_date": "2023-04-14", "album_cover": "https://i.scdn.co/image/ab67616d0000b27395ca6a9b4083a86c149934ae", "album_url": "https://open.spotify.com/album/6NcI39WPu4kY6Tul11nhSv", "danceability": 0.508, "energy": 0.43, "key": 2, "mode": 0, "speechiness": 0.0335, "acousticness": 0.83, "instrumentalness": 0.000441, "liveness": 0.093, "valence": 0.324, "tempo": 130.09, "artist_name": "David Kushner", "artist_url": "https://open.spotify.com/artist/33NVpKoXjItPwUJTMZIOiY", "country": "Latvia"}, {"name": "Standing Next to You", "popularity": 93, "explicit": false, "ranking": 7, "album_name": "GOLDEN", "album_release_date": "2023-11-03", "album_cover": "https://i.scdn.co/image/ab67616d0000b273741fd4807f442af3f7359316", "album_url": "https://open.spotify.com/album/5pSk3c3wVwnb2arb6ohCPU", "danceability": 0.711, "energy": 0.809, "key": 2, "mode": 0, "speechiness": 0.0955, "acousticness": 0.0447, "instrumentalness": 0, "liveness": 0.339, "valence": 0.816, "tempo": 106.017, "artist_name": "Jung Kook", "artist_url": "https://open.spotify.com/artist/6HaGTQPmzraVmaVxvz6EUc", "country": "Latvia"}, {"name": "fukumean", "popularity": 95, "explicit": true, "ranking": 8, "album_name": "a Gift & a Curse", "album_release_date": "2023-06-16", "album_cover": "https://i.scdn.co/image/ab67616d0000b273017d5e26552345c4b1575b6c", "album_url": "https://open.spotify.com/album/5qmZefgh78fN3jsyPPlvuw", "danceability": 0.847, "energy": 0.622, "key": 1, "mode": 0, "speechiness": 0.0903, "acousticness": 0.119, "instrumentalness": 0, "liveness": 0.285, "valence": 0.22, "tempo": 130.001, "artist_name": "Gunna", "artist_url": "https://open.spotify.com/artist/2hlmm7s2ICUX0LVIhVFlZQ", "country": "Latvia"}, {"name": "My Love Mine All Mine", "popularity": 97, "explicit": false, "ranking": 9, "album_name": "The Land Is Inhospitable and So Are We", "album_release_date": "2023-09-15", "album_cover": "https://i.scdn.co/image/ab67616d0000b27334f21d3047d85440dfa37f10", "album_url": "https://open.spotify.com/album/2Cn1d2KgbkAqbZCJ1RzdkA", "danceability": 0.504, "energy": 0.308, "key": 9, "mode": 1, "speechiness": 0.0321, "acousticness": 0.868, "instrumentalness": 0.135, "liveness": 0.158, "valence": 0.121, "tempo": 113.95, "artist_name": "Mitski", "artist_url": "https://open.spotify.com/artist/2uYWxilOVlUdk4oV9DvwqK", "country": "Latvia"}, {"name": "\u041f\u0440\u043e\u0449\u0430\u043d\u0438\u0435", "popularity": 66, "explicit": false, "ranking": 10, "album_name": "melancholia", "album_release_date": "2023-10-20", "album_cover": "https://i.scdn.co/image/ab67616d0000b2735a629671f673d863dd6cec70", "album_url": "https://open.spotify.com/album/4zuWO3wSh815WtZ4aqyWdi", "danceability": 0.479, "energy": 0.614, "key": 6, "mode": 0, "speechiness": 0.0304, "acousticness": 0.0171, "instrumentalness": 0.548, "liveness": 0.156, "valence": 0.258, "tempo": 96.027, "artist_name": "\u0422\u0440\u0438 \u0434\u043d\u044f \u0434\u043e\u0436\u0434\u044f", "artist_url": "https://open.spotify.com/artist/5q1NzLZwErZ9ujzqZKL0YZ", "country": "Latvia"}, {"name": "Sweater Weather", "popularity": 93, "explicit": false, "ranking": 11, "album_name": "I Love You.", "album_release_date": "2013-04-19", "album_cover": "https://i.scdn.co/image/ab67616d0000b2738265a736a1eb838ad5a0b921", "album_url": "https://open.spotify.com/album/4xkM0BwLM9H2IUcbYzpcBI", "danceability": 0.612, "energy": 0.807, "key": 10, "mode": 1, "speechiness": 0.0336, "acousticness": 0.0495, "instrumentalness": 0.0177, "liveness": 0.101, "valence": 0.398, "tempo": 124.053, "artist_name": "The Neighbourhood", "artist_url": "https://open.spotify.com/artist/77SW9BnxLY8rJ0RciFqkHh", "country": "Latvia"}, {"name": "ecstacy (slowed)", "popularity": 90, "explicit": true, "ranking": 12, "album_name": "ecstacy (slowed)", "album_release_date": "2023-06-06", "album_cover": "https://i.scdn.co/image/ab67616d0000b273cddfe70492c57a78e4d86b1c", "album_url": "https://open.spotify.com/album/6KLSjdqyjISLUhW8bx0Bqi", "danceability": 0.551, "energy": 0.677, "key": 2, "mode": 1, "speechiness": 0.0665, "acousticness": 0.0173, "instrumentalness": 0, "liveness": 0.381, "valence": 0.195, "tempo": 106.414, "artist_name": "SUICIDAL-IDOL", "artist_url": "https://open.spotify.com/artist/6KOszWgIriJLaPOySuBOTI", "country": "Latvia"}, {"name": "Haunted House", "popularity": 67, "explicit": true, "ranking": 13, "album_name": "AA LANGUAGE 2", "album_release_date": "2023-10-27", "album_cover": "https://i.scdn.co/image/ab67616d0000b273121e4de6551639bc5037324f", "album_url": "https://open.spotify.com/album/7IvfbDBurAnYpUC0w1h1Na", "danceability": 0.905, "energy": 0.726, "key": 8, "mode": 0, "speechiness": 0.0543, "acousticness": 0.0349, "instrumentalness": 0.00963, "liveness": 0.138, "valence": 0.677, "tempo": 150.031, "artist_name": "Aarne", "artist_url": "https://open.spotify.com/artist/5B5qmrbTFvA7TAxWruuwbo", "country": "Latvia"}, {"name": "No Role Modelz", "popularity": 91, "explicit": true, "ranking": 14, "album_name": "2014 Forest Hills Drive", "album_release_date": "2014-12-09", "album_cover": "https://i.scdn.co/image/ab67616d0000b273c6e0948bbb0681ff29cdbae8", "album_url": "https://open.spotify.com/album/0UMMIkurRUmkruZ3KGBLtG", "danceability": 0.69, "energy": 0.521, "key": 10, "mode": 0, "speechiness": 0.339, "acousticness": 0.324, "instrumentalness": 0, "liveness": 0.0534, "valence": 0.494, "tempo": 100.028, "artist_name": "J. Cole", "artist_url": "https://open.spotify.com/artist/6l3HvQ5sa6mXTsMTB19rO5", "country": "Latvia"}, {"name": "DEGVIELA", "popularity": 40, "explicit": false, "ranking": 15, "album_name": "SUPER", "album_release_date": "2023-10-10", "album_cover": "https://i.scdn.co/image/ab67616d0000b27359d491a22265b4b4a3dfa6a4", "album_url": "https://open.spotify.com/album/3e2kBXojxipDi0ItyCNx4e", "danceability": 0.751, "energy": 0.873, "key": 8, "mode": 1, "speechiness": 0.194, "acousticness": 0.249, "instrumentalness": 0, "liveness": 0.594, "valence": 0.718, "tempo": 134.95, "artist_name": "Singap\u016bras Sat\u012bns", "artist_url": "https://open.spotify.com/artist/3X4o7qy1ci4qtCVg2AtuXb", "country": "Latvia"}, {"name": "I Wanna Be Yours", "popularity": 95, "explicit": false, "ranking": 16, "album_name": "AM", "album_release_date": "2013-09-09", "album_cover": "https://i.scdn.co/image/ab67616d0000b2734ae1c4c5c45aabe565499163", "album_url": "https://open.spotify.com/album/78bpIziExqiI9qztvNFlQu", "danceability": 0.464, "energy": 0.417, "key": 0, "mode": 0, "speechiness": 0.0256, "acousticness": 0.136, "instrumentalness": 0.022, "liveness": 0.0974, "valence": 0.479, "tempo": 67.528, "artist_name": "Arctic Monkeys", "artist_url": "https://open.spotify.com/artist/7Ln80lUS6He07XvHI8qqHH", "country": "Latvia"}, {"name": "\u0417\u0438\u043c\u0430 \u0432 \u0441\u0435\u0440\u0434\u0446\u0435", "popularity": 58, "explicit": false, "ranking": 17, "album_name": "\u0418\u0437 \u0446\u0432\u0435\u0442\u043e\u0432 \u0438 \u0442\u0435\u043c\u043d\u043e\u0442\u044b", "album_release_date": "2022-12-16", "album_cover": "https://i.scdn.co/image/ab67616d0000b273abcab15ddf0f58bfea7b1a6d", "album_url": "https://open.spotify.com/album/5Psqb8umHXgLiEXpkAsYl4", "danceability": 0.66, "energy": 0.763, "key": 5, "mode": 0, "speechiness": 0.0351, "acousticness": 0.107, "instrumentalness": 0, "liveness": 0.229, "valence": 0.61, "tempo": 108.054, "artist_name": "Moya Mishel", "artist_url": "https://open.spotify.com/artist/28oFVU5sNejm6p76RkSwtQ", "country": "Latvia"}, {"name": "Seven (feat. Latto) (Explicit Ver.)", "popularity": 83, "explicit": true, "ranking": 18, "album_name": "GOLDEN", "album_release_date": "2023-11-03", "album_cover": "https://i.scdn.co/image/ab67616d0000b273741fd4807f442af3f7359316", "album_url": "https://open.spotify.com/album/5pSk3c3wVwnb2arb6ohCPU", "danceability": 0.79, "energy": 0.831, "key": 11, "mode": 1, "speechiness": 0.044, "acousticness": 0.312, "instrumentalness": 0, "liveness": 0.0797, "valence": 0.872, "tempo": 124.987, "artist_name": "Jung Kook", "artist_url": "https://open.spotify.com/artist/6HaGTQPmzraVmaVxvz6EUc", "country": "Latvia"}, {"name": "9mm", "popularity": 15, "explicit": true, "ranking": 19, "album_name": "Memphis Cult Vol. 6", "album_release_date": "2023-02-23", "album_cover": "https://i.scdn.co/image/ab67616d0000b2733818d94e3353a92945780d9c", "album_url": "https://open.spotify.com/album/5CZnhiTI3K85wLKwPLNOJB", "danceability": 0.737, "energy": 0.915, "key": 0, "mode": 1, "speechiness": 0.0412, "acousticness": 0.00322, "instrumentalness": 2.58e-05, "liveness": 0.084, "valence": 0.304, "tempo": 154.964, "artist_name": "Memphis Cult", "artist_url": "https://open.spotify.com/artist/6n9sdNb7mWvVmARDT6ujnJ", "country": "Latvia"}, {"name": "(It Goes Like) Nanana - Edit", "popularity": 91, "explicit": false, "ranking": 20, "album_name": "(It Goes Like) Nanana [Edit]", "album_release_date": "2023-06-15", "album_cover": "https://i.scdn.co/image/ab67616d0000b27388d71aadd009fe1a83df88f2", "album_url": "https://open.spotify.com/album/2LVDNOUUy2g8517ZEtQIcK", "danceability": 0.671, "energy": 0.876, "key": 7, "mode": 0, "speechiness": 0.0352, "acousticness": 0.12, "instrumentalness": 0.188, "liveness": 0.0823, "valence": 0.964, "tempo": 129.998, "artist_name": "Peggy Gou", "artist_url": "https://open.spotify.com/artist/2mLA48B366zkELXYx7hcDN", "country": "Latvia"}, {"name": "Flashing Lights", "popularity": 89, "explicit": true, "ranking": 21, "album_name": "Graduation", "album_release_date": "2007-09-11", "album_cover": "https://i.scdn.co/image/ab67616d0000b27326f7f19c7f0381e56156c94a", "album_url": "https://open.spotify.com/album/4SZko61aMnmgvNhfhgTuD3", "danceability": 0.639, "energy": 0.628, "key": 6, "mode": 0, "speechiness": 0.0399, "acousticness": 0.0381, "instrumentalness": 0, "liveness": 0.386, "valence": 0.43, "tempo": 90.482, "artist_name": "Kanye West", "artist_url": "https://open.spotify.com/artist/5K4W6rqBFWDnAN6FQUkS6x", "country": "Latvia"}, {"name": "The Night We Met", "popularity": 83, "explicit": false, "ranking": 22, "album_name": "Strange Trails", "album_release_date": "2015-04-07", "album_cover": "https://i.scdn.co/image/ab67616d0000b2739d2efe43d5b7ebc7cb60ca81", "album_url": "https://open.spotify.com/album/3yoNZlqerJnsnMN5EDwwBS", "danceability": 0.545, "energy": 0.366, "key": 2, "mode": 1, "speechiness": 0.0378, "acousticness": 0.969, "instrumentalness": 0.267, "liveness": 0.641, "valence": 0.1, "tempo": 86.997, "artist_name": "Lord Huron", "artist_url": "https://open.spotify.com/artist/6ltzsmQQbmdoHHbLZ4ZN25", "country": "Latvia"}, {"name": "Water", "popularity": 95, "explicit": false, "ranking": 23, "album_name": "Water", "album_release_date": "2023-07-28", "album_cover": "https://i.scdn.co/image/ab67616d0000b273d20231861e86a6f74ef2393e", "album_url": "https://open.spotify.com/album/22sXXkKgjEuawIFL1e1tRw", "danceability": 0.673, "energy": 0.722, "key": 3, "mode": 0, "speechiness": 0.0755, "acousticness": 0.0856, "instrumentalness": 0, "liveness": 0.137, "valence": 0.519, "tempo": 117.187, "artist_name": "Tyla", "artist_url": "https://open.spotify.com/artist/3SozjO3Lat463tQICI9LcE", "country": "Latvia"}, {"name": "JAA MAZAA ES SKAABAIS", "popularity": 44, "explicit": false, "ranking": 24, "album_name": "JAA MAZAA ES SKAABAIS", "album_release_date": "2023-05-05", "album_cover": "https://i.scdn.co/image/ab67616d0000b273480d708f786722adfdbeb7fa", "album_url": "https://open.spotify.com/album/2T7MHfFVIwVQlaFpiZzfXy", "danceability": 0.619, "energy": 0.63, "key": 11, "mode": 0, "speechiness": 0.0882, "acousticness": 0.0161, "instrumentalness": 0, "liveness": 0.155, "valence": 0.4, "tempo": 145.961, "artist_name": "$ourJ", "artist_url": "https://open.spotify.com/artist/4kkqGukpeagcuHEBdoV1pv", "country": "Latvia"}, {"name": "Another Love", "popularity": 92, "explicit": true, "ranking": 25, "album_name": "Long Way Down (Deluxe)", "album_release_date": "2013-06-24", "album_cover": "https://i.scdn.co/image/ab67616d0000b2731917a0f3f4152622a040913f", "album_url": "https://open.spotify.com/album/0Gf1yE895FKK4YWVRuAeg8", "danceability": 0.445, "energy": 0.537, "key": 4, "mode": 0, "speechiness": 0.04, "acousticness": 0.695, "instrumentalness": 1.65e-05, "liveness": 0.0944, "valence": 0.131, "tempo": 122.769, "artist_name": "Tom Odell", "artist_url": "https://open.spotify.com/artist/2txHhyCwHjUEpJjWrEyqyX", "country": "Latvia"}, {"name": "Why'd You Only Call Me When You're High?", "popularity": 90, "explicit": false, "ranking": 26, "album_name": "AM", "album_release_date": "2013-09-09", "album_cover": "https://i.scdn.co/image/ab67616d0000b2734ae1c4c5c45aabe565499163", "album_url": "https://open.spotify.com/album/78bpIziExqiI9qztvNFlQu", "danceability": 0.691, "energy": 0.631, "key": 2, "mode": 1, "speechiness": 0.0368, "acousticness": 0.0483, "instrumentalness": 1.13e-05, "liveness": 0.104, "valence": 0.8, "tempo": 92.004, "artist_name": "Arctic Monkeys", "artist_url": "https://open.spotify.com/artist/7Ln80lUS6He07XvHI8qqHH", "country": "Latvia"}, {"name": "Popular (with Playboi Carti & Madonna) - Music from the HBO Original Series", "popularity": 92, "explicit": true, "ranking": 27, "album_name": "Popular (Music from the HBO Original Series)", "album_release_date": "2023-06-02", "album_cover": "https://i.scdn.co/image/ab67616d0000b2734c8f092adc59b4bf4212389d", "album_url": "https://open.spotify.com/album/5O0zUvdnJr0RbWzLFneN2i", "danceability": 0.855, "energy": 0.678, "key": 1, "mode": 1, "speechiness": 0.189, "acousticness": 0.0569, "instrumentalness": 3.69e-05, "liveness": 0.412, "valence": 0.852, "tempo": 99.029, "artist_name": "The Weeknd", "artist_url": "https://open.spotify.com/artist/1Xyo4u8uXC1ZmMpatF05PJ", "country": "Latvia"}, {"name": "Hate It Or Love It", "popularity": 85, "explicit": true, "ranking": 28, "album_name": "The Documentary", "album_release_date": "2005", "album_cover": "https://i.scdn.co/image/ab67616d0000b273b1d860ab1ba847e778b2796d", "album_url": "https://open.spotify.com/album/4PrPbmm0gKvaD3rerOXFg8", "danceability": 0.802, "energy": 0.785, "key": 9, "mode": 1, "speechiness": 0.207, "acousticness": 0.14, "instrumentalness": 0, "liveness": 0.123, "valence": 0.435, "tempo": 99.998, "artist_name": "The Game", "artist_url": "https://open.spotify.com/artist/0NbfKEOTQCcwd6o7wSDOHI", "country": "Latvia"}, {"name": "Cruel Summer", "popularity": 99, "explicit": false, "ranking": 29, "album_name": "Lover", "album_release_date": "2019-08-23", "album_cover": "https://i.scdn.co/image/ab67616d0000b273e787cffec20aa2a396a61647", "album_url": "https://open.spotify.com/album/1NAmidJlEaVgA3MpcPFYGq", "danceability": 0.552, "energy": 0.702, "key": 9, "mode": 1, "speechiness": 0.157, "acousticness": 0.117, "instrumentalness": 2.06e-05, "liveness": 0.105, "valence": 0.564, "tempo": 169.994, "artist_name": "Taylor Swift", "artist_url": "https://open.spotify.com/artist/06HL4z0CvFAxyc27GXpf02", "country": "Latvia"}, {"name": "Is It Over Now? (Taylor's Version) (From The Vault)", "popularity": 93, "explicit": false, "ranking": 30, "album_name": "1989 (Taylor's Version)", "album_release_date": "2023-10-26", "album_cover": "https://i.scdn.co/image/ab67616d0000b273904445d70d04eb24d6bb79ac", "album_url": "https://open.spotify.com/album/64LU4c1nfjz1t4VnGhagcg", "danceability": 0.596, "energy": 0.658, "key": 0, "mode": 1, "speechiness": 0.036, "acousticness": 0.0504, "instrumentalness": 0, "liveness": 0.127, "valence": 0.176, "tempo": 100.012, "artist_name": "Taylor Swift", "artist_url": "https://open.spotify.com/artist/06HL4z0CvFAxyc27GXpf02", "country": "Latvia"}, {"name": "Heartless", "popularity": 89, "explicit": false, "ranking": 31, "album_name": "808s & Heartbreak", "album_release_date": "2008-11-24", "album_cover": "https://i.scdn.co/image/ab67616d0000b273346d77e155d854735410ed18", "album_url": "https://open.spotify.com/album/3WFTGIO6E3Xh4paEOBY9OU", "danceability": 0.79, "energy": 0.647, "key": 10, "mode": 0, "speechiness": 0.136, "acousticness": 0.0515, "instrumentalness": 0, "liveness": 0.248, "valence": 0.654, "tempo": 87.999, "artist_name": "Kanye West", "artist_url": "https://open.spotify.com/artist/5K4W6rqBFWDnAN6FQUkS6x", "country": "Latvia"}, {"name": "Stargirl Interlude", "popularity": 88, "explicit": false, "ranking": 32, "album_name": "Starboy", "album_release_date": "2016-11-24", "album_cover": "https://i.scdn.co/image/ab67616d0000b273a048415db06a5b6fa7ec4e1a", "album_url": "https://open.spotify.com/album/4AdZV63ycxFLF6Hcol0QnB", "danceability": 0.715, "energy": 0.47, "key": 5, "mode": 0, "speechiness": 0.0772, "acousticness": 0.353, "instrumentalness": 0.0923, "liveness": 0.104, "valence": 0.426, "tempo": 89.965, "artist_name": "The Weeknd", "artist_url": "https://open.spotify.com/artist/1Xyo4u8uXC1ZmMpatF05PJ", "country": "Latvia"}, {"name": "Pink + White", "popularity": 91, "explicit": false, "ranking": 33, "album_name": "Blonde", "album_release_date": "2016-08-20", "album_cover": "https://i.scdn.co/image/ab67616d0000b273c5649add07ed3720be9d5526", "album_url": "https://open.spotify.com/album/3mH6qwIy9crq0I9YQbOuDf", "danceability": 0.545, "energy": 0.545, "key": 9, "mode": 1, "speechiness": 0.107, "acousticness": 0.667, "instrumentalness": 5.48e-05, "liveness": 0.417, "valence": 0.549, "tempo": 159.94, "artist_name": "Frank Ocean", "artist_url": "https://open.spotify.com/artist/2h93pZq0e7k5yf4dywlkpM", "country": "Latvia"}, {"name": "As It Was", "popularity": 95, "explicit": false, "ranking": 34, "album_name": "Harry's House", "album_release_date": "2022-05-20", "album_cover": "https://i.scdn.co/image/ab67616d0000b2732e8ed79e177ff6011076f5f0", "album_url": "https://open.spotify.com/album/5r36AJ6VOJtp00oxSkBZ5h", "danceability": 0.52, "energy": 0.731, "key": 6, "mode": 0, "speechiness": 0.0557, "acousticness": 0.342, "instrumentalness": 0.00101, "liveness": 0.311, "valence": 0.662, "tempo": 173.93, "artist_name": "Harry Styles", "artist_url": "https://open.spotify.com/artist/6KImCVD70vtIoJWnq6nGn3", "country": "Latvia"}, {"name": "Uz Seen", "popularity": 45, "explicit": true, "ranking": 35, "album_name": "LUKSUS STONKS", "album_release_date": "2022-07-04", "album_cover": "https://i.scdn.co/image/ab67616d0000b27390739a0f12526a2650d9f714", "album_url": "https://open.spotify.com/album/3whiYXcPJw7mjnTM9mR9NV", "danceability": 0.683, "energy": 0.738, "key": 0, "mode": 1, "speechiness": 0.0315, "acousticness": 0.00575, "instrumentalness": 0, "liveness": 0.665, "valence": 0.769, "tempo": 117.443, "artist_name": "Singap\u016bras Sat\u012bns", "artist_url": "https://open.spotify.com/artist/3X4o7qy1ci4qtCVg2AtuXb", "country": "Latvia"}, {"name": "I'm Good (Blue)", "popularity": 92, "explicit": true, "ranking": 36, "album_name": "I'm Good (Blue)", "album_release_date": "2022-08-26", "album_cover": "https://i.scdn.co/image/ab67616d0000b273933c036cd61cd40d3f17a9c4", "album_url": "https://open.spotify.com/album/7M842DMhYVALrXsw3ty7B3", "danceability": 0.561, "energy": 0.965, "key": 7, "mode": 0, "speechiness": 0.0343, "acousticness": 0.00383, "instrumentalness": 7.07e-06, "liveness": 0.371, "valence": 0.304, "tempo": 128.04, "artist_name": "David Guetta", "artist_url": "https://open.spotify.com/artist/1Cs0zKBU1kc0i8ypK3B9ai", "country": "Latvia"}, {"name": "We Are The People", "popularity": 51, "explicit": false, "ranking": 37, "album_name": "Walking On A Dream", "album_release_date": "2008-01-01", "album_cover": "https://i.scdn.co/image/ab67616d0000b273410dfc8e880c1b3fefe6b83c", "album_url": "https://open.spotify.com/album/3qFui1PcteHFky44CeUflG", "danceability": 0.666, "energy": 0.785, "key": 4, "mode": 0, "speechiness": 0.0308, "acousticness": 0.0981, "instrumentalness": 0.0198, "liveness": 0.434, "valence": 0.549, "tempo": 122.973, "artist_name": "Empire of the Sun", "artist_url": "https://open.spotify.com/artist/67hb7towEyKvt5Z8Bx306c", "country": "Latvia"}, {"name": "Starboy", "popularity": 94, "explicit": true, "ranking": 38, "album_name": "Starboy", "album_release_date": "2016-11-25", "album_cover": "https://i.scdn.co/image/ab67616d0000b2734718e2b124f79258be7bc452", "album_url": "https://open.spotify.com/album/2ODvWsOgouMbaA5xf0RkJe", "danceability": 0.679, "energy": 0.587, "key": 7, "mode": 1, "speechiness": 0.276, "acousticness": 0.141, "instrumentalness": 6.35e-06, "liveness": 0.137, "valence": 0.486, "tempo": 186.003, "artist_name": "The Weeknd", "artist_url": "https://open.spotify.com/artist/1Xyo4u8uXC1ZmMpatF05PJ", "country": "Latvia"}, {"name": "I KNOW ?", "popularity": 92, "explicit": true, "ranking": 39, "album_name": "UTOPIA", "album_release_date": "2023-07-28", "album_cover": "https://i.scdn.co/image/ab67616d0000b273881d8d8378cd01099babcd44", "album_url": "https://open.spotify.com/album/18NOKLkZETa4sWwLMIm0UZ", "danceability": 0.927, "energy": 0.619, "key": 5, "mode": 0, "speechiness": 0.0539, "acousticness": 0.0186, "instrumentalness": 0, "liveness": 0.104, "valence": 0.817, "tempo": 117.995, "artist_name": "Travis Scott", "artist_url": "https://open.spotify.com/artist/0Y5tJX1MQlPlqiwlOH1tJY", "country": "Latvia"}, {"name": "Star Shopping", "popularity": 86, "explicit": true, "ranking": 40, "album_name": "Star Shopping", "album_release_date": "2015", "album_cover": "https://i.scdn.co/image/ab67616d0000b2736404fdef267b14d7a548f182", "album_url": "https://open.spotify.com/album/48dH5WaD1L379zPQt6LMDD", "danceability": 0.538, "energy": 0.471, "key": 4, "mode": 0, "speechiness": 0.0955, "acousticness": 0.0946, "instrumentalness": 0.0185, "liveness": 0.116, "valence": 0.307, "tempo": 93.07, "artist_name": "Lil Peep", "artist_url": "https://open.spotify.com/artist/2kCcBybjl3SAtIcwdWpUe3", "country": "Latvia"}, {"name": "Homecoming", "popularity": 85, "explicit": true, "ranking": 41, "album_name": "Graduation", "album_release_date": "2007-09-11", "album_cover": "https://i.scdn.co/image/ab67616d0000b27326f7f19c7f0381e56156c94a", "album_url": "https://open.spotify.com/album/4SZko61aMnmgvNhfhgTuD3", "danceability": 0.667, "energy": 0.747, "key": 1, "mode": 1, "speechiness": 0.189, "acousticness": 0.337, "instrumentalness": 0, "liveness": 0.115, "valence": 0.918, "tempo": 86.917, "artist_name": "Kanye West", "artist_url": "https://open.spotify.com/artist/5K4W6rqBFWDnAN6FQUkS6x", "country": "Latvia"}, {"name": "Dance The Night - From Barbie The Album", "popularity": 94, "explicit": false, "ranking": 42, "album_name": "Dance The Night (From Barbie The Album)", "album_release_date": "2023-05-25", "album_cover": "https://i.scdn.co/image/ab67616d0000b2737dd3ba455ee3390cb55b0192", "album_url": "https://open.spotify.com/album/5cH7FqB7JD5q1tJXJ7FHYu", "danceability": 0.671, "energy": 0.845, "key": 11, "mode": 0, "speechiness": 0.048, "acousticness": 0.0207, "instrumentalness": 0, "liveness": 0.329, "valence": 0.775, "tempo": 110.056, "artist_name": "Dua Lipa", "artist_url": "https://open.spotify.com/artist/6M2wZ9GZgrQXHCFfjv46we", "country": "Latvia"}, {"name": "Apocalypse", "popularity": 90, "explicit": false, "ranking": 43, "album_name": "Cigarettes After Sex", "album_release_date": "2017-06-09", "album_cover": "https://i.scdn.co/image/ab67616d0000b27312b69bf576f5e80291f75161", "album_url": "https://open.spotify.com/album/2mxFsS5yylSTHNivV53HoA", "danceability": 0.37, "energy": 0.467, "key": 5, "mode": 1, "speechiness": 0.0273, "acousticness": 0.0205, "instrumentalness": 0.572, "liveness": 0.109, "valence": 0.182, "tempo": 94.485, "artist_name": "Cigarettes After Sex", "artist_url": "https://open.spotify.com/artist/1QAJqy2dA3ihHBFIHRphZj", "country": "Latvia"}, {"name": "Money Trees", "popularity": 84, "explicit": true, "ranking": 44, "album_name": "good kid, m.A.A.d city", "album_release_date": "2012", "album_cover": "https://i.scdn.co/image/ab67616d0000b273d28d2ebdedb220e479743797", "album_url": "https://open.spotify.com/album/6PBZN8cbwkqm1ERj2BGXJ1", "danceability": 0.716, "energy": 0.531, "key": 7, "mode": 1, "speechiness": 0.122, "acousticness": 0.0703, "instrumentalness": 0, "liveness": 0.224, "valence": 0.344, "tempo": 71.994, "artist_name": "Kendrick Lamar", "artist_url": "https://open.spotify.com/artist/2YZyLoL8N0Wb9xBt1NhZWg", "country": "Latvia"}, {"name": "See You Again (feat. Kali Uchis)", "popularity": 92, "explicit": true, "ranking": 45, "album_name": "Flower Boy", "album_release_date": "2017-07-21", "album_cover": "https://i.scdn.co/image/ab67616d0000b2738940ac99f49e44f59e6f7fb3", "album_url": "https://open.spotify.com/album/2nkto6YNI4rUYTLqEwWJ3o", "danceability": 0.558, "energy": 0.559, "key": 6, "mode": 1, "speechiness": 0.0959, "acousticness": 0.371, "instrumentalness": 7.49e-06, "liveness": 0.109, "valence": 0.62, "tempo": 78.558, "artist_name": "Tyler, The Creator", "artist_url": "https://open.spotify.com/artist/4V8LLVI7PbaPR0K2TGSxFF", "country": "Latvia"}, {"name": "Lovers Rock", "popularity": 90, "explicit": false, "ranking": 46, "album_name": "French Exit", "album_release_date": "2014-06-05", "album_cover": "https://i.scdn.co/image/ab67616d0000b273e1bc1af856b42dd7fdba9f84", "album_url": "https://open.spotify.com/album/4Hai0uVzRbyTSaTPzxTY4e", "danceability": 0.559, "energy": 0.871, "key": 5, "mode": 0, "speechiness": 0.0397, "acousticness": 7.53e-06, "instrumentalness": 0.00545, "liveness": 0.096, "valence": 0.572, "tempo": 104.97, "artist_name": "TV Girl", "artist_url": "https://open.spotify.com/artist/0Y6dVaC9DZtPNH4591M42W", "country": "Latvia"}, {"name": "na Circus", "popularity": 58, "explicit": true, "ranking": 47, "album_name": "Cristoforo Colombo", "album_release_date": "2023-11-03", "album_cover": "https://i.scdn.co/image/ab67616d0000b273cccf10276da7b793666563dc", "album_url": "https://open.spotify.com/album/4PmKko0sUQl7I1cyeBD5Zg", "danceability": 0.811, "energy": 0.494, "key": 1, "mode": 1, "speechiness": 0.304, "acousticness": 0.252, "instrumentalness": 5.87e-06, "liveness": 0.0935, "valence": 0.217, "tempo": 120.985, "artist_name": "FRIENDLY THUG 52 NGG", "artist_url": "https://open.spotify.com/artist/5xtbUYHaOycg6HIi10EZdV", "country": "Latvia"}, {"name": "Too Many Nights (feat. Don Toliver & with Future)", "popularity": 89, "explicit": true, "ranking": 48, "album_name": "HEROES & VILLAINS", "album_release_date": "2022-12-02", "album_cover": "https://i.scdn.co/image/ab67616d0000b27313e54d6687e65678d60466c2", "album_url": "https://open.spotify.com/album/7txGsnDSqVMoRl6RQ9XyZP", "danceability": 0.684, "energy": 0.671, "key": 7, "mode": 0, "speechiness": 0.0464, "acousticness": 0.189, "instrumentalness": 2.37e-05, "liveness": 0.122, "valence": 0.156, "tempo": 88.048, "artist_name": "Metro Boomin", "artist_url": "https://open.spotify.com/artist/0iEtIxbK0KxaSlF7G42ZOp", "country": "Latvia"}, {"name": "Agora Hills", "popularity": 82, "explicit": true, "ranking": 49, "album_name": "Scarlet", "album_release_date": "2023-09-20", "album_cover": "https://i.scdn.co/image/ab67616d0000b273a840032f14ab22da396e43cb", "album_url": "https://open.spotify.com/album/1bBez9PNvkJPW08bU7NYta", "danceability": 0.755, "energy": 0.687, "key": 8, "mode": 0, "speechiness": 0.101, "acousticness": 0.183, "instrumentalness": 0.000177, "liveness": 0.125, "valence": 0.381, "tempo": 123.01, "artist_name": "Doja Cat", "artist_url": "https://open.spotify.com/artist/5cj0lLjcoR7YOSnhnX0Po5", "country": "Latvia"}, {"name": "SPIT IN MY FACE!", "popularity": 86, "explicit": true, "ranking": 50, "album_name": "SPIT IN MY FACE!", "album_release_date": "2022-12-20", "album_cover": "https://i.scdn.co/image/ab67616d0000b27360ddc59c8d590a37cf2348f3", "album_url": "https://open.spotify.com/album/2XurGuugADHAwF8gEYjtMA", "danceability": 0.73, "energy": 0.785, "key": 8, "mode": 1, "speechiness": 0.0554, "acousticness": 0.0464, "instrumentalness": 0.0216, "liveness": 0.111, "valence": 0.649, "tempo": 94.094, "artist_name": "ThxSoMch", "artist_url": "https://open.spotify.com/artist/4MvZhE1iuzttcoyepkpfdF", "country": "Latvia"}]